Workbook

Sheet Main Statistics
C8: Main Statistics | D8: Alt 1 | E8: Alt 2 | F8: Alt 3 | G8: Alt 4 | H8: Alt 5
C9: Mean NPV | D9: ='NPV - Allt.1'!I20 -> 3.0930249e+09 | E9: ='NPV - Allt.2'!K21 -> 3.1191679e+09 | F9: ='NPV - Allt.3'!P13 -> 2.957658e+09 | G9: ='NPV - Allt.4'!O11 -> 2.9608142e+09 | H9: ='NPV - Allt5.'!M13 -> 3.1435108e+09
C10: 95 % CL range | D10: ='NPV - Allt.1'!W26 -> 22467362 | E10: ='NPV - Allt.2'!X28 -> 27692377 | F10: ='NPV - Allt.3'!AD19 -> 16153996 | G10: ='NPV - Allt.4'!R17 -> 20032439 | H10: ='NPV - Allt5.'!AA19 -> 18540898
C11: Standard Deviation | D11: ='NPV - Allt.1'!I24 -> 1.8124832e+08 | E11: ='NPV - Allt.2'!K25 -> 2.2339947e+08 | F11: ='NPV - Allt.3'!P17 -> 1.3031724e+08 | G11: ='NPV - Allt.4'!O15 -> 1.6160535e+08 | H11: ='NPV - Allt5.'!M17 -> 1.4957282e+08
C12: Min | D12: ='NPV - Allt.1'!I29 -> 2.5214565e+09 | E12: ='NPV - Allt.2'!K30 -> 2.2263695e+09 | F12: ='NPV - Allt.3'!P22 -> 2.5593149e+09 | G12: ='NPV - Allt.4'!O20 -> 2.4204575e+09 | H12: ='NPV - Allt5.'!M22 -> 2.6249396e+09
C13: Max | D13: ='NPV - Allt.1'!I30 -> 3.6743832e+09 | E13: ='NPV - Allt.2'!K31 -> 3.7900394e+09 | F13: ='NPV - Allt.3'!P23 -> 3.3726707e+09 | G13: ='NPV - Allt.4'!O21 -> 3.4670212e+09 | H13: ='NPV - Allt5.'!M23 -> 3.6352797e+09
C14: Probability of NPV < 1,7 Billion | D14: ='NPV - Allt.1'!G20 -> 0 | E14: ='NPV - Allt.2'!H21 -> 0 | F14: ='NPV - Allt.3'!M12 -> 0 | G14: ='NPV - Allt.4'!L11 -> 0 | H14: ='NPV - Allt5.'!K9 -> 0
C15: Count | D15: 1000 | E15: 1000 | F15: 1000 | G15: 1000 | H15: 1000

Sheet Varity A - Carménère
AF1: Exponential distribution | AL1: Adjusting yield to deases risk
C2: All calculations related to Varity A - Carménère | M2: Annual Demand | T2: Farming tecniques: | W2: Material costs per hectar | AC2: Disese occurance | AF2: Traditonal | AI2: Modern | AL2: Traditional | AN2: Modern
M3: Mean | N3: 1.015 | T3: Traditional farming | U3: Modern farming | W3: Traditinal farming | Z3: Modern farming | AC3: 5 % probability of occuring each year | AF3: Lambda | AG3: 5 | AI3: 10 | AT3: Annual revenue | AV3: Costs | AX3: Disease events | AZ3: Yield | BB3: Profit per year
M4: STD | N4: 0.05 | S4: Annual fixed cost per hectar | T4: 3500000 | U4: 5500000 | W4: Mean | X4: 1300000 | Z4: Mean | AA4: 2000000 | AC4: 0 if it dosent occure, 1 if it does | AF4: Average | AG4: 0.1 | AI4: 0.2
S5: Effect on the annual yield in percentage | T5: 0.95 | U5: 1.1 | W5: STD | X5: 160000 | Z5: STD | AA5: 130000
S6: Total hectar per year | T6: 20 | U6: 20 | AC6: Year 1 | AD6: =IF(RAND() < 0.05, 1, 0) -> 0 | AF6: Year 1 | AG6: =IF(AD6=1, -LN(RAND()) / 5, 0) -> 0 | AI6: =IF(AD6=1, -LN(RAND()) / 10, 0) -> 0 | AK6: Year 1 | AL6: =T10 * (1 - AG6) -> 13.542828 | AN6: =U10 * (1 - AI6) -> 15.681169
C7: Price per ton - Normal distribution | F7: Annual yield (avkastning) - Triangular distribution | L7: Year 1 | M7: 200 | W7: Scaled mean | X7: 14.0725 | Z7: Scaled mean | AA7: 14.5066 | AC7: Year 2 | AD7: =IF(RAND() < 0.05, 1, 0) -> 0 | AF7: Year 2 | AG7: =IF(AD7=1, -LN(RAND()) / 5, 0) -> 0 | AI7: =IF(AD7=1, -LN(RAND()) / 10, 0) -> 0 | AK7: Year 2 | AL7: =T11 * (1 - AG7) -> 13.038875 | AN7: =U11 * (1 - AI7) -> 15.097645
C8: Mean | D8: 1500000 | F8: Min | G8: 8 | L8: Year 2 | M8: =M7 * _xlfn.NORM.INV(RAND(),N3,N4) -> 202.24749 | S8: Fixed cost per year (20 hectar) | T8: =T4*T6 -> 70000000 | U8: =U4*U6 -> 110000000 | W8: Scaled STD | X8: 0.12258 | Z8: Scaled STD | AA8: 0.0649 | AC8: Year 3 | AD8: =IF(RAND() < 0.05, 1, 0) -> 0 | AF8: Year 3 | AG8: =IF(AD8=1, -LN(RAND()) / 5, 0) -> 0 | AI8: =IF(AD8=1, -LN(RAND()) / 10, 0) -> 0 | AK8: Year 3 | AL8: =T12 * (1 - AG8) -> 14.876227 | AN8: =U12 * (1 - AI8) -> 17.225105
C9: STD | D9: 110000 | F9: Likely | G9: 13 | L9: Year 3 | M9: =M8 * _xlfn.NORM.INV(RAND(), N3,N4) -> 195.88246 | T9: Adjusted yield traditional | U9: Adjusted yield modern | AC9: Year 4 | AD9: =IF(RAND() < 0.05, 1, 0) -> 0 | AF9: Year 4 | AG9: =IF(AD9=1, -LN(RAND()) / 5, 0) -> 0 | AI9: =IF(AD9=1, -LN(RAND()) / 10, 0) -> 0 | AK9: Year 4 | AL9: =T13 * (1 - AG9) -> 11.703023 | AN9: =U13 * (1 - AI9) -> 13.550869 | AT9: Traditional | AU9: Modern | AV9: Traditonal | AW9: Modern | AX9: Traditional | AY9: Modern | AZ9: Traditional | BA9: Modern | BB9: Traditonal | BC9: Modern
F10: Max | G10: 18 | L10: Year 4 | M10: =M9 * _xlfn.NORM.INV(RAND(),N3,N4) -> 193.65322 | S10: Year 1 | T10: =G12*$T$5 -> 13.542828 | U10: =G12*$U$5 -> 15.681169 | AC10: Year 5 | AD10: =IF(RAND() < 0.05, 1, 0) -> 0 | AF10: Year 5 | AG10: =IF(AD10=1, -LN(RAND()) / 5, 0) -> 0 | AI10: =IF(AD10=1, -LN(RAND()) / 10, 0) -> 0 | AK10: Year 5 | AL10: =T14 * (1 - AG10) -> 14.693422 | AN10: =U14 * (1 - AI10) -> 17.013436 | AS10: Year 1 | AT10: =MIN(AL6,M7) * C11 * 20 -> 4.136699e+08 | AU10: =MIN(AN6,M7) * C11 * 20 -> 4.789862e+08 | AV10: =$T$8 + X14 * 20 -> 95030228 | AW10: =$U$8+AA14 * 20 -> 1.4770631e+08 | AX10: =SUM(AD6:AD25) -> 1 | AY10: =SUM(AD6:AD25) -> 1 | AZ10: =AL6 -> 13.542828 | BA10: =AN6 -> 15.681169 | BB10: =AT10-AV10 -> 3.1863967e+08 | BC10: =AU10-AW10 -> 3.312799e+08
B11: Year 1 | C11: =_xlfn.NORM.INV(RAND(),1500000,110000) -> 1527265.6 | L11: Year 5 | M11: =M10 * _xlfn.NORM.INV(RAND(),N3,N4) -> 214.22804 | S11: Year 2 | T11: =G13*$T$5 -> 13.038875 | U11: =G13*$U$5 -> 15.097645 | AC11: Year 6 | AD11: =IF(RAND() < 0.05, 1, 0) -> 0 | AF11: Year 6 | AG11: =IF(AD11=1, -LN(RAND()) / 5, 0) -> 0 | AI11: =IF(AD11=1, -LN(RAND()) / 10, 0) -> 0 | AK11: Year 6 | AL11: =T15 * (1 - AG11) -> 10.676203 | AN11: =U15 * (1 - AI11) -> 12.361919 | AS11: Year 2 | AT11: =MIN(AL7,M8) * C12 * 20 -> 4.174718e+08 | AU11: =MIN(AN7,M8) * C12 * 20 -> 4.833884e+08 | AV11: =$T$8 + X15 * 20 -> 1.0048232e+08 | AW11: =$U$8+AA15 * 20 -> 1.4954647e+08 | AZ11: =AL7 -> 13.038875 | BA11: =AN7 -> 15.097645 | BB11: =AT11-AV11 -> 3.1698948e+08 | BC11: =AU11-AW11 -> 3.3384194e+08
B12: Year 2 | C12: =_xlfn.NORM.INV(RAND(),1500000,110000) -> 1600873.6 | F12: Year 1 | G12: =IF(RAND() < (13 - 8) / (18 - 8), 8 + SQRT(RAND()) * (13 - 8), 18 - SQRT(RAND()) * (18 - 13)) -> 14.255608 | L12: Year 6 | M12: =M11 * _xlfn.NORM.INV(RAND(), N3,N4) -> 203.65983 | S12: Year 3 | T12: =G14*$T$5 -> 14.876227 | U12: =G14*$U$5 -> 17.225105 | W12: Traditional | Z12: Modern | AC12: Year 7 | AD12: =IF(RAND() < 0.05, 1, 0) -> 0 | AF12: Year 7 | AG12: =IF(AD12=1, -LN(RAND()) / 5, 0) -> 0 | AI12: =IF(AD12=1, -LN(RAND()) / 10, 0) -> 0 | AK12: Year 7 | AL12: =T16 * (1 - AG12) -> 10.448539 | AN12: =U16 * (1 - AI12) -> 12.098309 | AS12: Year 3 | AT12: =MIN(AL8,M9) * C13 * 20 -> 4.6105959e+08 | AU12: =MIN(AN8,M9) * C13 * 20 -> 5.3385847e+08 | AV12: =$T$8 + X16 * 20 -> 92736904 | AW12: =$U$8+AA16 * 20 -> 1.4780721e+08 | AZ12: =AL8 -> 14.876227 | BA12: =AN8 -> 17.225105 | BB12: =AT12-AV12 -> 3.6832268e+08 | BC12: =AU12-AW12 -> 3.8605126e+08
B13: Year 3 | C13: =_xlfn.NORM.INV(RAND(),1500000,110000) -> 1549652.3 | F13: Year 2 | G13: =IF(RAND() < (13 - 8) / (18 - 8), 8 + SQRT(RAND()) * (13 - 8), 18 - SQRT(RAND()) * (18 - 13)) -> 13.725131 | L13: Year 7 | M13: =M12 * _xlfn.NORM.INV(RAND(), N3, N4) -> 234.1254 | S13: Year 4 | T13: =G15*$T$5 -> 11.703023 | U13: =G15*$U$5 -> 13.550869 | AC13: Year 8 | AD13: =IF(RAND() < 0.05, 1, 0) -> 0 | AF13: Year 8 | AG13: =IF(AD13=1, -LN(RAND()) / 5, 0) -> 0 | AI13: =IF(AD13=1, -LN(RAND()) / 10, 0) -> 0 | AK13: Year 8 | AL13: =T17 * (1 - AG13) -> 15.139465 | AN13: =U17 * (1 - AI13) -> 17.529906 | AS13: Year 4 | AT13: =MIN(AL9,M10) * C14 * 20 -> 3.2816413e+08 | AU13: =MIN(AN9,M10) * C14 * 20 -> 3.7997952e+08 | AV13: =$T$8 + X17 * 20 -> 1.0165328e+08 | AW13: =$U$8+AA17 * 20 -> 1.522217e+08 | AZ13: =AL9 -> 11.703023 | BA13: =AN9 -> 13.550869 | BB13: =AT13-AV13 -> 2.2651084e+08 | BC13: =AU13-AW13 -> 2.2775782e+08
B14: Year 4 | C14: =_xlfn.NORM.INV(RAND(),1500000,110000) -> 1402048.5 | F14: Year 3 | G14: =IF(RAND() < (13 - 8) / (18 - 8), 8 + SQRT(RAND()) * (13 - 8), 18 - SQRT(RAND()) * (18 - 13)) -> 15.659186 | L14: Year 8 | M14: =M13 * _xlfn.NORM.INV(RAND(), N3, N4) -> 239.84243 | S14: Year 5 | T14: =G16*$T$5 -> 14.693422 | U14: =G16*$U$5 -> 17.013436 | W14: Year 1 | X14: =_xlfn.LOGNORM.INV(RAND(),$X$7,$X$8) -> 1251511.4 | Z14: Year 1 | AA14: =_xlfn.LOGNORM.INV(RAND(),$AA$7,$AA$8) -> 1885315.3 | AC14: Year 9 | AD14: =IF(RAND() < 0.05, 1, 0) -> 0 | AF14: Year 9 | AG14: =IF(AD14=1, -LN(RAND()) / 5, 0) -> 0 | AI14: =IF(AD14=1, -LN(RAND()) / 10, 0) -> 0 | AK14: Year 9 | AL14: =T18 * (1 - AG14) -> 13.055747 | AN14: =U18 * (1 - AI14) -> 15.117181 | AS14: Year 5 | AT14: =MIN(AL10,M11) * C15 * 20 -> 4.5764426e+08 | AU14: =MIN(AN10,M11) * C15 * 20 -> 5.2990388e+08 | AV14: =$T$8 + X18 * 20 -> 92768170 | AW14: =$U$8+AA18 * 20 -> 1.5269522e+08 | AZ14: =AL10 -> 14.693422 | BA14: =AN10 -> 17.013436 | BB14: =AT14-AV14 -> 3.6487609e+08 | BC14: =AU14-AW14 -> 3.7720866e+08
B15: Year 5 | C15: =_xlfn.NORM.INV(RAND(),1500000,110000) -> 1557310 | F15: Year 4 | G15: =IF(RAND() < (13 - 8) / (18 - 8), 8 + SQRT(RAND()) * (13 - 8), 18 - SQRT(RAND()) * (18 - 13)) -> 12.318972 | L15: Year 9 | M15: =M14 * _xlfn.NORM.INV(RAND(), N3, N4) -> 246.30273 | S15: Year 6 | T15: =G17*$T$5 -> 10.676203 | U15: =G17*$U$5 -> 12.361919 | W15: Year 2 | X15: =_xlfn.LOGNORM.INV(RAND(),$X$7,$X$8) -> 1524116.1 | Z15: Year 2 | AA15: =_xlfn.LOGNORM.INV(RAND(),$AA$7,$AA$8) -> 1977323.3 | AC15: Year 10 | AD15: =IF(RAND() < 0.05, 1, 0) -> 1 | AF15: Year 10 | AG15: =IF(AD15=1, -LN(RAND()) / 5, 0) -> 0.10182146 | AI15: =IF(AD15=1, -LN(RAND()) / 10, 0) -> 0.11627212 | AK15: Year 10 | AL15: =T19 * (1 - AG15) -> 10.427167 | AN15: =U19 * (1 - AI15) -> 11.879312 | AS15: Year 6 | AT15: =MIN(AL11,M12) * C16 * 20 -> 2.7162392e+08 | AU15: =MIN(AN11,M12) * C16 * 20 -> 3.145119e+08 | AV15: =$T$8 + X19 * 20 -> 96455903 | AW15: =$U$8+AA19 * 20 -> 1.5131402e+08 | AZ15: =AL11 -> 10.676203 | BA15: =AN11 -> 12.361919 | BB15: =AT15-AV15 -> 1.7516801e+08 | BC15: =AU15-AW15 -> 1.6319788e+08
B16: Year 6 | C16: =_xlfn.NORM.INV(RAND(),1500000,110000) -> 1272099.8 | F16: Year 5 | G16: =IF(RAND() < (13 - 8) / (18 - 8), 8 + SQRT(RAND()) * (13 - 8), 18 - SQRT(RAND()) * (18 - 13)) -> 15.46676 | L16: Year 10 | M16: =M15 * _xlfn.NORM.INV(RAND(),N3,N4) -> 240.83044 | S16: Year 7 | T16: =G18*$T$5 -> 10.448539 | U16: =G18*$U$5 -> 12.098309 | W16: Year 3 | X16: =_xlfn.LOGNORM.INV(RAND(),$X$7,$X$8) -> 1136845.2 | Z16: Year 3 | AA16: =_xlfn.LOGNORM.INV(RAND(),$AA$7,$AA$8) -> 1890360.5 | AC16: Year 11 | AD16: =IF(RAND() < 0.05, 1, 0) -> 0 | AF16: Year 11 | AG16: =IF(AD16=1, -LN(RAND()) / 5, 0) -> 0 | AI16: =IF(AD16=1, -LN(RAND()) / 10, 0) -> 0 | AK16: Year 11 | AL16: =T20 * (1 - AG16) -> 15.136538 | AN16: =U20 * (1 - AI16) -> 17.526517 | AS16: Year 7 | AT16: =MIN(AL12,M13) * C17 * 20 -> 2.9072562e+08 | AU16: =MIN(AN12,M13) * C17 * 20 -> 3.3662966e+08 | AV16: =$T$8 + X20 * 20 -> 97367781 | AW16: =$U$8+AA20 * 20 -> 1.536483e+08 | AZ16: =AL12 -> 10.448539 | BA16: =AN12 -> 12.098309 | BB16: =AT16-AV16 -> 1.9335784e+08 | BC16: =AU16-AW16 -> 1.8298137e+08
B17: Year 7 | C17: =_xlfn.NORM.INV(RAND(),1500000,110000) -> 1391226.1 | F17: Year 6 | G17: =IF(RAND() < (13 - 8) / (18 - 8), 8 + SQRT(RAND()) * (13 - 8), 18 - SQRT(RAND()) * (18 - 13)) -> 11.238108 | L17: Year 11 | M17: =M16 * _xlfn.NORM.INV(RAND(),N3,N4) -> 239.49412 | S17: Year 8 | T17: =G19*$T$5 -> 15.139465 | U17: =G19*$U$5 -> 17.529906 | W17: Year 4 | X17: =_xlfn.LOGNORM.INV(RAND(),$X$7,$X$8) -> 1582664.2 | Z17: Year 4 | AA17: =_xlfn.LOGNORM.INV(RAND(),$AA$7,$AA$8) -> 2111084.9 | AC17: Year 12 | AD17: =IF(RAND() < 0.05, 1, 0) -> 0 | AF17: Year 12 | AG17: =IF(AD17=1, -LN(RAND()) / 5, 0) -> 0 | AI17: =IF(AD17=1, -LN(RAND()) / 10, 0) -> 0 | AK17: Year 12 | AL17: =T21 * (1 - AG17) -> 9.9041003 | AN17: =U21 * (1 - AI17) -> 11.467906 | AS17: Year 8 | AT17: =MIN(AL13,M14) * C18 * 20 -> 3.9228966e+08 | AU17: =MIN(AN13,M14) * C18 * 20 -> 4.5423013e+08 | AV17: =$T$8 + X21 * 20 -> 96366408 | AW17: =$U$8+AA21 * 20 -> 1.4749191e+08 | AZ17: =AL13 -> 15.139465 | BA17: =AN13 -> 17.529906 | BB17: =AT17-AV17 -> 2.9592325e+08 | BC17: =AU17-AW17 -> 3.0673822e+08
B18: Year 8 | C18: =_xlfn.NORM.INV(RAND(),1500000,110000) -> 1295586.3 | F18: Year 7 | G18: =IF(RAND() < (13 - 8) / (18 - 8), 8 + SQRT(RAND()) * (13 - 8), 18 - SQRT(RAND()) * (18 - 13)) -> 10.998462 | L18: Year 12 | M18: =M17 * _xlfn.NORM.INV(RAND(),N3,N4) -> 262.48667 | S18: Year 9 | T18: =G20*$T$5 -> 13.055747 | U18: =G20*$U$5 -> 15.117181 | W18: Year 5 | X18: =_xlfn.LOGNORM.INV(RAND(),$X$7,$X$8) -> 1138408.5 | Z18: Year 5 | AA18: =_xlfn.LOGNORM.INV(RAND(),$AA$7,$AA$8) -> 2134760.9 | AC18: Year 13 | AD18: =IF(RAND() < 0.05, 1, 0) -> 0 | AF18: Year 13 | AG18: =IF(AD18=1, -LN(RAND()) / 5, 0) -> 0 | AI18: =IF(AD18=1, -LN(RAND()) / 10, 0) -> 0 | AK18: Year 13 | AL18: =T22 * (1 - AG18) -> 8.0149548 | AN18: =U22 * (1 - AI18) -> 9.280474 | AS18: Year 9 | AT18: =MIN(AL14,M15) * C19 * 20 -> 3.9873593e+08 | AU18: =MIN(AN14,M15) * C19 * 20 -> 4.6169423e+08 | AV18: =$T$8 + X22 * 20 -> 93613401 | AW18: =$U$8+AA22 * 20 -> 1.4600329e+08 | AZ18: =AL14 -> 13.055747 | BA18: =AN14 -> 15.117181 | BB18: =AT18-AV18 -> 3.0512252e+08 | BC18: =AU18-AW18 -> 3.1569094e+08
B19: Year 9 | C19: =_xlfn.NORM.INV(RAND(),1500000,110000) -> 1527051.4 | F19: Year 8 | G19: =IF(RAND() < (13 - 8) / (18 - 8), 8 + SQRT(RAND()) * (13 - 8), 18 - SQRT(RAND()) * (18 - 13)) -> 15.936279 | L19: Year 13 | M19: =M18*_xlfn.NORM.INV(RAND(), N3,N4) -> 253.79627 | S19: Year 10 | T19: =G21*$T$5 -> 11.609236 | U19: =G21*$U$5 -> 13.442273 | W19: Year 6 | X19: =_xlfn.LOGNORM.INV(RAND(),$X$7,$X$8) -> 1322795.1 | Z19: Year 6 | AA19: =_xlfn.LOGNORM.INV(RAND(),$AA$7,$AA$8) -> 2065701.2 | AC19: Year 14 | AD19: =IF(RAND() < 0.05, 1, 0) -> 0 | AF19: Year 14 | AG19: =IF(AD19=1, -LN(RAND()) / 5, 0) -> 0 | AI19: =IF(AD19=1, -LN(RAND()) / 10, 0) -> 0 | AK19: Year 14 | AL19: =T23 * (1 - AG19) -> 14.446589 | AN19: =U23 * (1 - AI19) -> 16.72763 | AS19: Year 10 | AT19: =MIN(AL15,M16) * C20 * 20 -> 3.2320543e+08 | AU19: =MIN(AN15,M16) * C20 * 20 -> 3.682168e+08 | AV19: =$T$8 + X23 * 20 -> 90879640 | AW19: =$U$8+AA23 * 20 -> 1.473593e+08 | AZ19: =AL15 -> 10.427167 | BA19: =AN15 -> 11.879312 | BB19: =AT19-AV19 -> 2.3232579e+08 | BC19: =AU19-AW19 -> 2.2085751e+08
B20: Year 10 | C20: =_xlfn.NORM.INV(RAND(),1500000,110000) -> 1549823.8 | F20: Year 9 | G20: =IF(RAND() < (13 - 8) / (18 - 8), 8 + SQRT(RAND()) * (13 - 8), 18 - SQRT(RAND()) * (18 - 13)) -> 13.742891 | L20: Year 14 | M20: =M19 * _xlfn.NORM.INV(RAND(),N3,N4) -> 261.3982 | S20: Year 11 | T20: =G22*$T$5 -> 15.136538 | U20: =G22*$U$5 -> 17.526517 | W20: Year 7 | X20: =_xlfn.LOGNORM.INV(RAND(),$X$7,$X$8) -> 1368389.1 | Z20: Year 7 | AA20: =_xlfn.LOGNORM.INV(RAND(),$AA$7,$AA$8) -> 2182414.8 | AC20: Year 15 | AD20: =IF(RAND() < 0.05, 1, 0) -> 0 | AF20: Year 15 | AG20: =IF(AD20=1, -LN(RAND()) / 5, 0) -> 0 | AI20: =IF(AD20=1, -LN(RAND()) / 10, 0) -> 0 | AK20: Year 15 | AL20: =T24 * (1 - AG20) -> 13.786376 | AN20: =U24 * (1 - AI20) -> 15.963172 | AS20: Year 11 | AT20: =MIN(AL16,M17) * C21 * 20 -> 4.3152618e+08 | AU20: =MIN(AN16,M17) * C21 * 20 -> 4.9966189e+08 | AV20: =$T$8 + X24 * 20 -> 91496749 | AW20: =$U$8+AA24 * 20 -> 1.5496944e+08 | AZ20: =AL16 -> 15.136538 | BA20: =AN16 -> 17.526517 | BB20: =AT20-AV20 -> 3.4002943e+08 | BC20: =AU20-AW20 -> 3.4469245e+08
B21: Year 11 | C21: =_xlfn.NORM.INV(RAND(),1500000,110000) -> 1425445.5 | F21: Year 10 | G21: =IF(RAND() < (13 - 8) / (18 - 8), 8 + SQRT(RAND()) * (13 - 8), 18 - SQRT(RAND()) * (18 - 13)) -> 12.220249 | L21: Year 15 | M21: =M20 * _xlfn.NORM.INV(RAND(),N3,N4) -> 250.22929 | S21: Year 12 | T21: =G23*$T$5 -> 9.9041003 | U21: =G23*$U$5 -> 11.467906 | W21: Year 8 | X21: =_xlfn.LOGNORM.INV(RAND(),$X$7,$X$8) -> 1318320.4 | Z21: Year 8 | AA21: =_xlfn.LOGNORM.INV(RAND(),$AA$7,$AA$8) -> 1874595.5 | AC21: Year 16 | AD21: =IF(RAND() < 0.05, 1, 0) -> 0 | AF21: Year 16 | AG21: =IF(AD21=1, -LN(RAND()) / 5, 0) -> 0 | AI21: =IF(AD21=1, -LN(RAND()) / 10, 0) -> 0 | AK21: Year 16 | AL21: =T25 * (1 - AG21) -> 13.295829 | AN21: =U25 * (1 - AI21) -> 15.395171 | AS21: Year 12 | AT21: =MIN(AL17,M18) * C22 * 20 -> 2.8919465e+08 | AU21: =MIN(AN17,M18) * C22 * 20 -> 3.3485697e+08 | AV21: =$T$8 + X25 * 20 -> 97807152 | AW21: =$U$8+AA25 * 20 -> 1.4680743e+08 | AZ21: =AL17 -> 9.9041003 | BA21: =AN17 -> 11.467906 | BB21: =AT21-AV21 -> 1.913875e+08 | BC21: =AU21-AW21 -> 1.8804954e+08
B22: Year 12 | C22: =_xlfn.NORM.INV(RAND(),1500000,110000) -> 1459974.4 | F22: Year 11 | G22: =IF(RAND() < (13 - 8) / (18 - 8), 8 + SQRT(RAND()) * (13 - 8), 18 - SQRT(RAND()) * (18 - 13)) -> 15.933198 | L22: Year 16 | M22: =M21 * _xlfn.NORM.INV(RAND(), N3,N4) -> 243.225 | S22: Year 13 | T22: =G24*$T$5 -> 8.0149548 | U22: =G24*$U$5 -> 9.280474 | W22: Year 9 | X22: =_xlfn.LOGNORM.INV(RAND(),$X$7,$X$8) -> 1180670.1 | Z22: Year 9 | AA22: =_xlfn.LOGNORM.INV(RAND(),$AA$7,$AA$8) -> 1800164.7 | AC22: Year 17 | AD22: =IF(RAND() < 0.05, 1, 0) -> 0 | AF22: Year 17 | AG22: =IF(AD22=1, -LN(RAND()) / 5, 0) -> 0 | AI22: =IF(AD22=1, -LN(RAND()) / 10, 0) -> 0 | AK22: Year 17 | AL22: =T26 * (1 - AG22) -> 13.05661 | AN22: =U26 * (1 - AI22) -> 15.11818 | AS22: Year 13 | AT22: =MIN(AL18,M19) * C23 * 20 -> 3.0329659e+08 | AU22: =MIN(AN18,M19) * C23 * 20 -> 3.5118553e+08 | AV22: =$T$8 + X26 * 20 -> 95407710 | AW22: =$U$8+AA26 * 20 -> 1.4970074e+08 | AZ22: =AL18 -> 8.0149548 | BA22: =AN18 -> 9.280474 | BB22: =AT22-AV22 -> 2.0788888e+08 | BC22: =AU22-AW22 -> 2.0148478e+08
B23: Year 13 | C23: =_xlfn.NORM.INV(RAND(),1500000,110000) -> 1892066.7 | F23: Year 12 | G23: =IF(RAND() < (13 - 8) / (18 - 8), 8 + SQRT(RAND()) * (13 - 8), 18 - SQRT(RAND()) * (18 - 13)) -> 10.425369 | L23: Year 17 | M23: =M22 * _xlfn.NORM.INV(RAND(),N3,N4) -> 249.31482 | S23: Year 14 | T23: =G25*$T$5 -> 14.446589 | U23: =G25*$U$5 -> 16.72763 | W23: Year 10 | X23: =_xlfn.LOGNORM.INV(RAND(),$X$7,$X$8) -> 1043982 | Z23: Year 10 | AA23: =_xlfn.LOGNORM.INV(RAND(),$AA$7,$AA$8) -> 1867964.8 | AC23: Year 18 | AD23: =IF(RAND() < 0.05, 1, 0) -> 0 | AF23: Year 18 | AG23: =IF(AD23=1, -LN(RAND()) / 5, 0) -> 0 | AI23: =IF(AD23=1, -LN(RAND()) / 10, 0) -> 0 | AK23: Year 18 | AL23: =T27 * (1 - AG23) -> 10.64665 | AN23: =U27 * (1 - AI23) -> 12.327699 | AS23: Year 14 | AT23: =MIN(AL19,M20) * C24 * 20 -> 4.7287073e+08 | AU23: =MIN(AN19,M20) * C24 * 20 -> 5.4753453e+08 | AV23: =$T$8 + X27 * 20 -> 95101476 | AW23: =$U$8+AA27 * 20 -> 1.4976952e+08 | AZ23: =AL19 -> 14.446589 | BA23: =AN19 -> 16.72763 | BB23: =AT23-AV23 -> 3.7776926e+08 | BC23: =AU23-AW23 -> 3.9776502e+08
B24: Year 14 | C24: =_xlfn.NORM.INV(RAND(),1500000,110000) -> 1636617.2 | F24: Year 13 | G24: =IF(RAND() < (13 - 8) / (18 - 8), 8 + SQRT(RAND()) * (13 - 8), 18 - SQRT(RAND()) * (18 - 13)) -> 8.4367946 | L24: Year 18 | M24: =M23 * _xlfn.NORM.INV(RAND(),N3,N4) -> 252.59139 | S24: Year 15 | T24: =G26*$T$5 -> 13.786376 | U24: =G26*$U$5 -> 15.963172 | W24: Year 11 | X24: =_xlfn.LOGNORM.INV(RAND(),$X$7,$X$8) -> 1074837.5 | Z24: Year 11 | AA24: =_xlfn.LOGNORM.INV(RAND(),$AA$7,$AA$8) -> 2248471.8 | AC24: Year 19 | AD24: =IF(RAND() < 0.05, 1, 0) -> 0 | AF24: Year 19 | AG24: =IF(AD24=1, -LN(RAND()) / 5, 0) -> 0 | AI24: =IF(AD24=1, -LN(RAND()) / 10, 0) -> 0 | AK24: Year 19 | AL24: =T28 * (1 - AG24) -> 16.397948 | AN24: =U28 * (1 - AI24) -> 18.987098 | AS24: Year 15 | AT24: =MIN(AL20,M21) * C25 * 20 -> 4.6808069e+08 | AU24: =MIN(AN20,M21) * C25 * 20 -> 5.4198816e+08 | AV24: =$T$8 + X28 * 20 -> 95373959 | AW24: =$U$8+AA28 * 20 -> 1.4884917e+08 | AZ24: =AL20 -> 13.786376 | BA24: =AN20 -> 15.963172 | BB24: =AT24-AV24 -> 3.7270673e+08 | BC24: =AU24-AW24 -> 3.9313899e+08
B25: Year 15 | C25: =_xlfn.NORM.INV(RAND(),1500000,110000) -> 1697620.5 | F25: Year 14 | G25: =IF(RAND() < (13 - 8) / (18 - 8), 8 + SQRT(RAND()) * (13 - 8), 18 - SQRT(RAND()) * (18 - 13)) -> 15.206936 | L25: Year 19 | M25: =M24 * _xlfn.NORM.INV(RAND(),N3,N4) -> 240.51204 | S25: Year 16 | T25: =G27*$T$5 -> 13.295829 | U25: =G27*$U$5 -> 15.395171 | W25: Year 12 | X25: =_xlfn.LOGNORM.INV(RAND(),$X$7,$X$8) -> 1390357.6 | Z25: Year 12 | AA25: =_xlfn.LOGNORM.INV(RAND(),$AA$7,$AA$8) -> 1840371.4 | AC25: Year 20 | AD25: =IF(RAND() < 0.05, 1, 0) -> 0 | AF25: Year 20 | AG25: =IF(AD25=1, -LN(RAND()) / 5, 0) -> 0 | AI25: =IF(AD25=1, -LN(RAND()) / 10, 0) -> 0 | AK25: Year 20 | AL25: =T29 * (1 - AG25) -> 9.8049696 | AN25: =U29 * (1 - AI25) -> 11.353123 | AS25: Year 16 | AT25: =MIN(AL21,M22) * C26 * 20 -> 4.0887739e+08 | AU25: =MIN(AN21,M22) * C26 * 20 -> 4.7343697e+08 | AV25: =$T$8 + X29 * 20 -> 99427532 | AW25: =$U$8+AA29 * 20 -> 1.5095201e+08 | AZ25: =AL21 -> 13.295829 | BA25: =AN21 -> 15.395171 | BB25: =AT25-AV25 -> 3.0944985e+08 | BC25: =AU25-AW25 -> 3.2248496e+08
B26: Year 16 | C26: =_xlfn.NORM.INV(RAND(),1500000,110000) -> 1537615.2 | F26: Year 15 | G26: =IF(RAND() < (13 - 8) / (18 - 8), 8 + SQRT(RAND()) * (13 - 8), 18 - SQRT(RAND()) * (18 - 13)) -> 14.511974 | L26: Year 20 | M26: =M25 * _xlfn.NORM.INV(RAND(),N3,N4) -> 255.85265 | S26: Year 17 | T26: =G28*$T$5 -> 13.05661 | U26: =G28*$U$5 -> 15.11818 | W26: Year 13 | X26: =_xlfn.LOGNORM.INV(RAND(),$X$7,$X$8) -> 1270385.5 | Z26: Year 13 | AA26: =_xlfn.LOGNORM.INV(RAND(),$AA$7,$AA$8) -> 1985037.1 | AS26: Year 17 | AT26: =MIN(AL22,M23) * C27 * 20 -> 3.9269311e+08 | AU26: =MIN(AN22,M23) * C27 * 20 -> 4.5469728e+08 | AV26: =$T$8 + X30 * 20 -> 92802736 | AW26: =$U$8+AA30 * 20 -> 1.4673919e+08 | AZ26: =AL22 -> 13.05661 | BA26: =AN22 -> 15.11818 | BB26: =AT26-AV26 -> 2.9989037e+08 | BC26: =AU26-AW26 -> 3.0795809e+08
B27: Year 17 | C27: =_xlfn.NORM.INV(RAND(),1500000,110000) -> 1503809.6 | F27: Year 16 | G27: =IF(RAND() < (13 - 8) / (18 - 8), 8 + SQRT(RAND()) * (13 - 8), 18 - SQRT(RAND()) * (18 - 13)) -> 13.99561 | S27: Year 18 | T27: =G29*$T$5 -> 10.64665 | U27: =G29*$U$5 -> 12.327699 | W27: Year 14 | X27: =_xlfn.LOGNORM.INV(RAND(),$X$7,$X$8) -> 1255073.8 | Z27: Year 14 | AA27: =_xlfn.LOGNORM.INV(RAND(),$AA$7,$AA$8) -> 1988475.8 | AS27: Year 18 | AT27: =MIN(AL23,M24) * C28 * 20 -> 3.1073924e+08 | AU27: =MIN(AN23,M24) * C28 * 20 -> 3.5980333e+08 | AV27: =$T$8 + X31 * 20 -> 93326392 | AW27: =$U$8+AA31 * 20 -> 1.4898798e+08 | AZ27: =AL23 -> 10.64665 | BA27: =AN23 -> 12.327699 | BB27: =AT27-AV27 -> 2.1741285e+08 | BC27: =AU27-AW27 -> 2.1081535e+08
B28: Year 18 | C28: =_xlfn.NORM.INV(RAND(),1500000,110000) -> 1459328.8 | F28: Year 17 | G28: =IF(RAND() < (13 - 8) / (18 - 8), 8 + SQRT(RAND()) * (13 - 8), 18 - SQRT(RAND()) * (18 - 13)) -> 13.7438 | S28: Year 19 | T28: =G30*$T$5 -> 16.397948 | U28: =G30*$U$5 -> 18.987098 | W28: Year 15 | X28: =_xlfn.LOGNORM.INV(RAND(),$X$7,$X$8) -> 1268698 | Z28: Year 15 | AA28: =_xlfn.LOGNORM.INV(RAND(),$AA$7,$AA$8) -> 1942458.6 | AS28: Year 19 | AT28: =MIN(AL24,M25) * C29 * 20 -> 4.7980165e+08 | AU28: =MIN(AN24,M25) * C29 * 20 -> 5.555598e+08 | AV28: =$T$8 + X32 * 20 -> 92781866 | AW28: =$U$8+AA32 * 20 -> 1.4680235e+08 | AZ28: =AL24 -> 16.397948 | BA28: =AN24 -> 18.987098 | BB28: =AT28-AV28 -> 3.8701978e+08 | BC28: =AU28-AW28 -> 4.0875745e+08
B29: Year 19 | C29: =_xlfn.NORM.INV(RAND(),1500000,110000) -> 1462992.9 | F29: Year 18 | G29: =IF(RAND() < (13 - 8) / (18 - 8), 8 + SQRT(RAND()) * (13 - 8), 18 - SQRT(RAND()) * (18 - 13)) -> 11.207 | S29: Year 20 | T29: =G31*$T$5 -> 9.8049696 | U29: =G31*$U$5 -> 11.353123 | W29: Year 16 | X29: =_xlfn.LOGNORM.INV(RAND(),$X$7,$X$8) -> 1471376.6 | Z29: Year 16 | AA29: =_xlfn.LOGNORM.INV(RAND(),$AA$7,$AA$8) -> 2047600.4 | AS29: Year 20 | AT29: =MIN(AL25,M26) * C30 * 20 -> 3.0480893e+08 | AU29: =MIN(AN25,M26) * C30 * 20 -> 3.5293666e+08 | AV29: =$T$8 + X33 * 20 -> 98548775 | AW29: =$U$8+AA33 * 20 -> 1.5217447e+08 | AZ29: =AL25 -> 9.8049696 | BA29: =AN25 -> 11.353123 | BB29: =AT29-AV29 -> 2.0626016e+08 | BC29: =AU29-AW29 -> 2.0076219e+08
B30: Year 20 | C30: =_xlfn.NORM.INV(RAND(),1500000,110000) -> 1554359.4 | F30: Year 19 | G30: =IF(RAND() < (13 - 8) / (18 - 8), 8 + SQRT(RAND()) * (13 - 8), 18 - SQRT(RAND()) * (18 - 13)) -> 17.260998 | W30: Year 17 | X30: =_xlfn.LOGNORM.INV(RAND(),$X$7,$X$8) -> 1140136.8 | Z30: Year 17 | AA30: =_xlfn.LOGNORM.INV(RAND(),$AA$7,$AA$8) -> 1836959.7
F31: Year 20 | G31: =IF(RAND() < (13 - 8) / (18 - 8), 8 + SQRT(RAND()) * (13 - 8), 18 - SQRT(RAND()) * (18 - 13)) -> 10.321021 | W31: Year 18 | X31: =_xlfn.LOGNORM.INV(RAND(),$X$7,$X$8) -> 1166319.6 | Z31: Year 18 | AA31: =_xlfn.LOGNORM.INV(RAND(),$AA$7,$AA$8) -> 1949398.9
W32: Year 19 | X32: =_xlfn.LOGNORM.INV(RAND(),$X$7,$X$8) -> 1139093.3 | Z32: Year 19 | AA32: =_xlfn.LOGNORM.INV(RAND(),$AA$7,$AA$8) -> 1840117.6
W33: Year 20 | X33: =_xlfn.LOGNORM.INV(RAND(),$X$7,$X$8) -> 1427438.8 | Z33: Year 20 | AA33: =_xlfn.LOGNORM.INV(RAND(),$AA$7,$AA$8) -> 2108723.6

Sheet Varity B - Cabarnet Savignon
B2: Varity B - Cabarnet Savignon | Q2: Material costs per hectar | W2: Disese occurance | Z2: Exponential distribution | AF2: Adjusting yield to deases risk
Q3: Traditinal farming | T3: Modern farming | W3: 5 % probability of occuring each year | Z3: Traditonal | AC3: Modern | AF3: Traditional | AH3: Modern
B4: Annual Yield | C4: Triangular distribution | F4: Price per ton | G4: Normal distribution | J4: Annual demand | K4: Normal distribution | N4: Farming tecniques: | Q4: Mean | R4: CLP 1 600 000,00 | T4: Mean | U4: 2500000 | W4: 0 if it dosent occure, 1 if it does | Z4: Lambda | AA4: 5 | AC4: 10
N5: Traditional farming | O5: Modern farming | Q5: STD | R5: CLP 200 000,00 | T5: STD | U5: 180000 | Z5: Average | AA5: 0.1 | AC5: 0.2 | AN5: Annual revenue | AP5: Costs | AR5: Disease events | AT5: Yield | AV5: Profit per year
B6: Min | C6: 5 | F6: Mean | G6: 1900000 | J6: Mean | K6: STD | M6: Annual fixed cost per hectar | N6: 3500000 | O6: 5500000 | W6: Year 1 | X6: =IF(RAND() < 0.05, 1, 0) -> 0
B7: Most likely | C7: 10 | F7: STD | G7: 250000 | J7: 0.985 | K7: 0.04 | M7: Effect on the annual yield in percentage | N7: 0.95 | O7: 1.1 | Q7: Scaled mean | R7: 14.27 | T7: Scaled mean | U7: 14.73 | W7: Year 2 | X7: =IF(RAND() < 0.05, 1, 0) -> 0 | Z7: Year 1 | AA7: =IF(X6=1, -LN(RAND()) / 5, 0) -> 0 | AC7: =IF(X6=1, -LN(RAND()) / 10, 0) -> 0 | AE7: Year 1 | AF7: =N12 * (1 - AA7) -> 11.883303 | AH7: =O12 * (1 - AC7) -> 13.759614
B8: Max | C8: 14 | M8: Total hectar per year | N8: 20 | O8: 20 | Q8: Scaled STD | R8: 0.124 | T8: Scaled STD | U8: 0.071 | W8: Year 3 | X8: =IF(RAND() < 0.05, 1, 0) -> 0 | Z8: Year 2 | AA8: =IF(X7=1, -LN(RAND()) / 5, 0) -> 0 | AC8: =IF(X7=1, -LN(RAND()) / 10, 0) -> 0 | AE8: Year 2 | AF8: =N13 * (1 - AA8) -> 10.728738 | AH8: =O13 * (1 - AC8) -> 12.422749
W9: Year 4 | X9: =IF(RAND() < 0.05, 1, 0) -> 0 | Z9: Year 3 | AA9: =IF(X8=1, -LN(RAND()) / 5, 0) -> 0 | AC9: =IF(X8=1, -LN(RAND()) / 10, 0) -> 0 | AE9: Year 3 | AF9: =N14 * (1 - AA9) -> 10.799913 | AH9: =O14 * (1 - AC9) -> 12.505162
B10: Year 1 | C10: =IF(RAND() < (10-5)/(14-5), 5 + SQRT(RAND() * (10-5) * (14-5)), 14 - SQRT((1-RAND()) * (14-10) * (14-5))) -> 12.50874 | F10: Year 1 | G10: =_xlfn.NORM.INV(RAND(),1900000,250000) -> 1678366.3 | I10: Year 1 | J10: 180 | M10: Fixed cost per year | N10: =N6*N8 -> 70000000 | O10: =O6*O8 -> 110000000 | W10: Year 5 | X10: =IF(RAND() < 0.05, 1, 0) -> 0 | Z10: Year 4 | AA10: =IF(X9=1, -LN(RAND()) / 5, 0) -> 0 | AC10: =IF(X9=1, -LN(RAND()) / 10, 0) -> 0 | AE10: Year 4 | AF10: =N15 * (1 - AA10) -> 7.9795886 | AH10: =O15 * (1 - AC10) -> 9.2395237
B11: Year 2 | C11: =IF(RAND() < (10-5)/(14-5), 5 + SQRT(RAND() * (10-5) * (14-5)), 14 - SQRT((1-RAND()) * (14-10) * (14-5))) -> 11.293408 | F11: Year 2 | G11: =_xlfn.NORM.INV(RAND(),1900000,250000) -> 1871125.8 | I11: Year 2 | J11: =J10 * _xlfn.NORM.INV(RAND(),$J$7,$K$7) -> 184.12717 | N11: Adjusted yield traditional | O11: Adjusted yield modern | W11: Year 6 | X11: =IF(RAND() < 0.05, 1, 0) -> 0 | Z11: Year 5 | AA11: =IF(X10=1, -LN(RAND()) / 5, 0) -> 0 | AC11: =IF(X10=1, -LN(RAND()) / 10, 0) -> 0 | AE11: Year 5 | AF11: =N16 * (1 - AA11) -> 9.0516924 | AH11: =O16 * (1 - AC11) -> 10.480907 | AN11: Traditional | AO11: Modern | AP11: Traditonal | AQ11: Modern | AR11: Traditional | AS11: Modern | AT11: Traditional | AU11: Modern | AV11: Traditonal | AW11: Modern
B12: Year 3 | C12: =IF(RAND() < (10-5)/(14-5), 5 + SQRT(RAND() * (10-5) * (14-5)), 14 - SQRT((1-RAND()) * (14-10) * (14-5))) -> 11.368329 | F12: Year 3 | G12: =_xlfn.NORM.INV(RAND(),1900000,250000) -> 2421909 | I12: Year 3 | J12: =J11 * _xlfn.NORM.INV(RAND(),$J$7,$K$7) -> 186.23002 | M12: Year 1 | N12: =C10*$N$7 -> 11.883303 | O12: =C10*$O$7 -> 13.759614 | Q12: Year 1 | R12: =_xlfn.LOGNORM.INV(RAND(),$R$7,$R$8) -> 1376102.5 | T12: Year 1 | U12: =_xlfn.LOGNORM.INV(RAND(),$U$7,$U$8) -> 2520503.1 | W12: Year 7 | X12: =IF(RAND() < 0.05, 1, 0) -> 0 | Z12: Year 6 | AA12: =IF(X11=1, -LN(RAND()) / 5, 0) -> 0 | AC12: =IF(X11=1, -LN(RAND()) / 10, 0) -> 0 | AE12: Year 6 | AF12: =N17 * (1 - AA12) -> 8.8855182 | AH12: =O17 * (1 - AC12) -> 10.288495 | AM12: Year 1 | AN12: =MIN(AF7,J10) * G10 * 20 -> 3.988907e+08 | AO12: =MIN(AH7,J10) * G10 * 20 -> 4.6187344e+08 | AP12: =$N$10 + R12 * 20 -> 97522050 | AQ12: =$O$10 + U12 * 20 -> 1.6041006e+08 | AR12: =SUM(X6:X25) -> 4 | AS12: =SUM(X6:X25) -> 4 | AT12: =AF7 -> 11.883303 | AU12: =AH7 -> 13.759614 | AV12: =AN12 - AP12 -> 3.0136865e+08 | AW12: =AO12 - AQ12 -> 3.0146338e+08
B13: Year 4 | C13: =IF(RAND() < (10-5)/(14-5), 5 + SQRT(RAND() * (10-5) * (14-5)), 14 - SQRT((1-RAND()) * (14-10) * (14-5))) -> 8.399567 | F13: Year 4 | G13: =_xlfn.NORM.INV(RAND(),1900000,250000) -> 1924355.7 | I13: Year 4 | J13: =J12 * _xlfn.NORM.INV(RAND(),$J$7,$K$7) -> 178.86942 | M13: Year 2 | N13: =C11*$N$7 -> 10.728738 | O13: =C11*$O$7 -> 12.422749 | Q13: Year 2 | R13: =_xlfn.LOGNORM.INV(RAND(),$R$7,$R$8) -> 1356954.6 | T13: Year 2 | U13: =_xlfn.LOGNORM.INV(RAND(),$U$7,$U$8) -> 2754808.9 | W13: Year 8 | X13: =IF(RAND() < 0.05, 1, 0) -> 0 | Z13: Year 7 | AA13: =IF(X12=1, -LN(RAND()) / 5, 0) -> 0 | AC13: =IF(X12=1, -LN(RAND()) / 10, 0) -> 0 | AE13: Year 7 | AF13: =N18 * (1 - AA13) -> 10.215445 | AH13: =O18 * (1 - AC13) -> 11.82841 | AM13: Year 2 | AN13: =MIN(AF8,J11) * G11 * 20 -> 4.0149636e+08 | AO13: =MIN(AH8,J11) * G11 * 20 -> 4.6489052e+08 | AP13: =$N$10 + R13 * 20 -> 97139092 | AQ13: =$O$10 + U13 * 20 -> 1.6509618e+08 | AT13: =AF8 -> 10.728738 | AU13: =AH8 -> 12.422749 | AV13: =AN13-AP13 -> 3.0435726e+08 | AW13: =AO13-AQ13 -> 2.9979434e+08
B14: Year 5 | C14: =IF(RAND() < (10-5)/(14-5), 5 + SQRT(RAND() * (10-5) * (14-5)), 14 - SQRT((1-RAND()) * (14-10) * (14-5))) -> 9.5280972 | F14: Year 5 | G14: =_xlfn.NORM.INV(RAND(),1900000,250000) -> 1736220.1 | I14: Year 5 | J14: =J13 * _xlfn.NORM.INV(RAND(),$J$7,$K$7) -> 186.8964 | M14: Year 3 | N14: =C12*$N$7 -> 10.799913 | O14: =C12*$O$7 -> 12.505162 | Q14: Year 3 | R14: =_xlfn.LOGNORM.INV(RAND(),$R$7,$R$8) -> 1793790.7 | T14: Year 3 | U14: =_xlfn.LOGNORM.INV(RAND(),$U$7,$U$8) -> 2473500.5 | W14: Year 9 | X14: =IF(RAND() < 0.05, 1, 0) -> 1 | Z14: Year 8 | AA14: =IF(X13=1, -LN(RAND()) / 5, 0) -> 0 | AC14: =IF(X13=1, -LN(RAND()) / 10, 0) -> 0 | AE14: Year 8 | AF14: =N19 * (1 - AA14) -> 9.0799509 | AH14: =O19 * (1 - AC14) -> 10.513627 | AM14: Year 3 | AN14: =MIN(AF9,J12) * G12 * 20 -> 5.2312813e+08 | AO14: =MIN(AH9,J12) * G12 * 20 -> 6.0572731e+08 | AP14: =$N$10 + R14 * 20 -> 1.0587581e+08 | AQ14: =$O$10 + U14 * 20 -> 1.5947001e+08 | AT14: =AF9 -> 10.799913 | AU14: =AH9 -> 12.505162 | AV14: =AN14-AP14 -> 4.1725232e+08 | AW14: =AO14-AQ14 -> 4.462573e+08
B15: Year 6 | C15: =IF(RAND() < (10-5)/(14-5), 5 + SQRT(RAND() * (10-5) * (14-5)), 14 - SQRT((1-RAND()) * (14-10) * (14-5))) -> 9.353177 | F15: Year 6 | G15: =_xlfn.NORM.INV(RAND(),1900000,250000) -> 1840769.2 | I15: Year 6 | J15: =J14 * _xlfn.NORM.INV(RAND(),$J$7,$K$7) -> 185.07071 | M15: Year 4 | N15: =C13*$N$7 -> 7.9795886 | O15: =C13*$O$7 -> 9.2395237 | Q15: Year 4 | R15: =_xlfn.LOGNORM.INV(RAND(),$R$7,$R$8) -> 1520825.5 | T15: Year 4 | U15: =_xlfn.LOGNORM.INV(RAND(),$U$7,$U$8) -> 2249378.8 | W15: Year 10 | X15: =IF(RAND() < 0.05, 1, 0) -> 0 | Z15: Year 9 | AA15: =IF(X14=1, -LN(RAND()) / 5, 0) -> 0.31484033 | AC15: =IF(X14=1, -LN(RAND()) / 10, 0) -> 0.10504025 | AE15: Year 9 | AF15: =N20 * (1 - AA15) -> 5.647545 | AH15: =O20 * (1 - AC15) -> 8.5416249 | AM15: Year 4 | AN15: =MIN(AF10,J13) * G13 * 20 -> 3.0711133e+08 | AO15: =MIN(AH10,J13) * G13 * 20 -> 3.556026e+08 | AP15: =$N$10 + R15 * 20 -> 1.0041651e+08 | AQ15: =$O$10 + U15 * 20 -> 1.5498758e+08 | AT15: =AF10 -> 7.9795886 | AU15: =AH10 -> 9.2395237 | AV15: =AN15-AP15 -> 2.0669482e+08 | AW15: =AO15-AQ15 -> 2.0061502e+08
B16: Year 7 | C16: =IF(RAND() < (10-5)/(14-5), 5 + SQRT(RAND() * (10-5) * (14-5)), 14 - SQRT((1-RAND()) * (14-10) * (14-5))) -> 10.7531 | F16: Year 7 | G16: =_xlfn.NORM.INV(RAND(),1900000,250000) -> 1700822.9 | I16: Year 7 | J16: =J15 * _xlfn.NORM.INV(RAND(),$J$7,$K$7) -> 185.19257 | M16: Year 5 | N16: =C14*$N$7 -> 9.0516924 | O16: =C14*$O$7 -> 10.480907 | Q16: Year 5 | R16: =_xlfn.LOGNORM.INV(RAND(),$R$7,$R$8) -> 1530531.1 | T16: Year 5 | U16: =_xlfn.LOGNORM.INV(RAND(),$U$7,$U$8) -> 2344967.9 | W16: Year 11 | X16: =IF(RAND() < 0.05, 1, 0) -> 0 | Z16: Year 10 | AA16: =IF(X15=1, -LN(RAND()) / 5, 0) -> 0 | AC16: =IF(X15=1, -LN(RAND()) / 10, 0) -> 0 | AE16: Year 10 | AF16: =N21 * (1 - AA16) -> 5.5296099 | AH16: =O21 * (1 - AC16) -> 6.4027062 | AM16: Year 5 | AN16: =MIN(AF11,J14) * G14 * 20 -> 3.1431461e+08 | AO16: =MIN(AH11,J14) * G14 * 20 -> 3.6394323e+08 | AP16: =$N$10 + R16 * 20 -> 1.0061062e+08 | AQ16: =$O$10 + U16 * 20 -> 1.5689936e+08 | AT16: =AF11 -> 9.0516924 | AU16: =AH11 -> 10.480907 | AV16: =AN16-AP16 -> 2.1370399e+08 | AW16: =AO16-AQ16 -> 2.0704387e+08
B17: Year 8 | C17: =IF(RAND() < (10-5)/(14-5), 5 + SQRT(RAND() * (10-5) * (14-5)), 14 - SQRT((1-RAND()) * (14-10) * (14-5))) -> 9.5578431 | F17: Year 8 | G17: =_xlfn.NORM.INV(RAND(),1900000,250000) -> 1869133.8 | I17: Year 8 | J17: =J16 * _xlfn.NORM.INV(RAND(),$J$7,$K$7) -> 180.25862 | M17: Year 6 | N17: =C15*$N$7 -> 8.8855182 | O17: =C15*$O$7 -> 10.288495 | Q17: Year 6 | R17: =_xlfn.LOGNORM.INV(RAND(),$R$7,$R$8) -> 1709959.3 | T17: Year 6 | U17: =_xlfn.LOGNORM.INV(RAND(),$U$7,$U$8) -> 2178890 | W17: Year 12 | X17: =IF(RAND() < 0.05, 1, 0) -> 0 | Z17: Year 11 | AA17: =IF(X16=1, -LN(RAND()) / 5, 0) -> 0 | AC17: =IF(X16=1, -LN(RAND()) / 10, 0) -> 0 | AE17: Year 11 | AF17: =N22 * (1 - AA17) -> 7.6698654 | AH17: =O22 * (1 - AC17) -> 8.8808968 | AM17: Year 6 | AN17: =MIN(AF12,J15) * G15 * 20 -> 3.2712377e+08 | AO17: =MIN(AH12,J15) * G15 * 20 -> 3.7877489e+08 | AP17: =$N$10 + R17 * 20 -> 1.0419919e+08 | AQ17: =$O$10 + U17 * 20 -> 1.535778e+08 | AT17: =AF12 -> 8.8855182 | AU17: =AH12 -> 10.288495 | AV17: =AN17-AP17 -> 2.2292459e+08 | AW17: =AO17-AQ17 -> 2.2519709e+08
B18: Year 9 | C18: =IF(RAND() < (10-5)/(14-5), 5 + SQRT(RAND() * (10-5) * (14-5)), 14 - SQRT((1-RAND()) * (14-10) * (14-5))) -> 8.6764947 | F18: Year 9 | G18: =_xlfn.NORM.INV(RAND(),1900000,250000) -> 2398732.1 | I18: Year 9 | J18: =J17 * _xlfn.NORM.INV(RAND(),$J$7,$K$7) -> 173.61968 | M18: Year 7 | N18: =C16*$N$7 -> 10.215445 | O18: =C16*$O$7 -> 11.82841 | Q18: Year 7 | R18: =_xlfn.LOGNORM.INV(RAND(),$R$7,$R$8) -> 1409333.8 | T18: Year 7 | U18: =_xlfn.LOGNORM.INV(RAND(),$U$7,$U$8) -> 2829888.3 | W18: Year 13 | X18: =IF(RAND() < 0.05, 1, 0) -> 0 | Z18: Year 12 | AA18: =IF(X17=1, -LN(RAND()) / 5, 0) -> 0 | AC18: =IF(X17=1, -LN(RAND()) / 10, 0) -> 0 | AE18: Year 12 | AF18: =N23 * (1 - AA18) -> 8.8388759 | AH18: =O23 * (1 - AC18) -> 10.234488 | AM18: Year 7 | AN18: =MIN(AF13,J16) * G16 * 20 -> 3.4749326e+08 | AO18: =MIN(AH13,J16) * G16 * 20 -> 4.0236062e+08 | AP18: =$N$10 + R18 * 20 -> 98186675 | AQ18: =$O$10 + U18 * 20 -> 1.6659777e+08 | AT18: =AF13 -> 10.215445 | AU18: =AH13 -> 11.82841 | AV18: =AN18-AP18 -> 2.4930659e+08 | AW18: =AO18-AQ18 -> 2.3576285e+08
B19: Year 10 | C19: =IF(RAND() < (10-5)/(14-5), 5 + SQRT(RAND() * (10-5) * (14-5)), 14 - SQRT((1-RAND()) * (14-10) * (14-5))) -> 5.820642 | F19: Year 10 | G19: =_xlfn.NORM.INV(RAND(),1900000,250000) -> 1901940.4 | I19: Year 10 | J19: =J18 * _xlfn.NORM.INV(RAND(),$J$7,$K$7) -> 184.02845 | M19: Year 8 | N19: =C17*$N$7 -> 9.0799509 | O19: =C17*$O$7 -> 10.513627 | Q19: Year 8 | R19: =_xlfn.LOGNORM.INV(RAND(),$R$7,$R$8) -> 1594106 | T19: Year 8 | U19: =_xlfn.LOGNORM.INV(RAND(),$U$7,$U$8) -> 2435652.2 | W19: Year 14 | X19: =IF(RAND() < 0.05, 1, 0) -> 0 | Z19: Year 13 | AA19: =IF(X18=1, -LN(RAND()) / 5, 0) -> 0 | AC19: =IF(X18=1, -LN(RAND()) / 10, 0) -> 0 | AE19: Year 13 | AF19: =N24 * (1 - AA19) -> 8.842148 | AH19: =O24 * (1 - AC19) -> 10.238277 | AM19: Year 8 | AN19: =MIN(AF14,J17) * G17 * 20 -> 3.3943287e+08 | AO19: =MIN(AH14,J17) * G17 * 20 -> 3.9302753e+08 | AP19: =$N$10 + R19 * 20 -> 1.0188212e+08 | AQ19: =$O$10 + U19 * 20 -> 1.5871304e+08 | AT19: =AF14 -> 9.0799509 | AU19: =AH14 -> 10.513627 | AV19: =AN19-AP19 -> 2.3755075e+08 | AW19: =AO19-AQ19 -> 2.3431449e+08
B20: Year 11 | C20: =IF(RAND() < (10-5)/(14-5), 5 + SQRT(RAND() * (10-5) * (14-5)), 14 - SQRT((1-RAND()) * (14-10) * (14-5))) -> 8.0735426 | F20: Year 11 | G20: =_xlfn.NORM.INV(RAND(),1900000,250000) -> 1828089 | I20: Year 11 | J20: =J19 * _xlfn.NORM.INV(RAND(),$J$7,$K$7) -> 187.03368 | M20: Year 9 | N20: =C18*$N$7 -> 8.24267 | O20: =C18*$O$7 -> 9.5441442 | Q20: Year 9 | R20: =_xlfn.LOGNORM.INV(RAND(),$R$7,$R$8) -> 1387495 | T20: Year 9 | U20: =_xlfn.LOGNORM.INV(RAND(),$U$7,$U$8) -> 2247921.9 | W20: Year 15 | X20: =IF(RAND() < 0.05, 1, 0) -> 0 | Z20: Year 14 | AA20: =IF(X19=1, -LN(RAND()) / 5, 0) -> 0 | AC20: =IF(X19=1, -LN(RAND()) / 10, 0) -> 0 | AE20: Year 14 | AF20: =N25 * (1 - AA20) -> 6.3438678 | AH20: =O25 * (1 - AC20) -> 7.3455311 | AM20: Year 9 | AN20: =MIN(AF15,J18) * G18 * 20 -> 2.7093895e+08 | AO20: =MIN(AH15,J18) * G18 * 20 -> 4.0978139e+08 | AP20: =$N$10 + R20 * 20 -> 97749900 | AQ20: =$O$10 + U20 * 20 -> 1.5495844e+08 | AT20: =AF15 -> 5.647545 | AU20: =AH15 -> 8.5416249 | AV20: =AN20-AP20 -> 1.7318905e+08 | AW20: =AO20-AQ20 -> 2.5482296e+08
B21: Year 12 | C21: =IF(RAND() < (10-5)/(14-5), 5 + SQRT(RAND() * (10-5) * (14-5)), 14 - SQRT((1-RAND()) * (14-10) * (14-5))) -> 9.3040798 | F21: Year 12 | G21: =_xlfn.NORM.INV(RAND(),1900000,250000) -> 2157967.3 | I21: Year 12 | J21: =J20 * _xlfn.NORM.INV(RAND(),$J$7,$K$7) -> 189.28968 | M21: Year 10 | N21: =C19*$N$7 -> 5.5296099 | O21: =C19*$O$7 -> 6.4027062 | Q21: Year 10 | R21: =_xlfn.LOGNORM.INV(RAND(),$R$7,$R$8) -> 1889676.2 | T21: Year 10 | U21: =_xlfn.LOGNORM.INV(RAND(),$U$7,$U$8) -> 2523359.5 | W21: Year 16 | X21: =IF(RAND() < 0.05, 1, 0) -> 0 | Z21: Year 15 | AA21: =IF(X20=1, -LN(RAND()) / 5, 0) -> 0 | AC21: =IF(X20=1, -LN(RAND()) / 10, 0) -> 0 | AE21: Year 15 | AF21: =N26 * (1 - AA21) -> 10.825104 | AH21: =O26 * (1 - AC21) -> 12.534331 | AM21: Year 10 | AN21: =MIN(AF16,J19) * G19 * 20 -> 2.1033977e+08 | AO21: =MIN(AH16,J19) * G19 * 20 -> 2.4355131e+08 | AP21: =$N$10 + R21 * 20 -> 1.0779352e+08 | AQ21: =$O$10 + U21 * 20 -> 1.6046719e+08 | AT21: =AF16 -> 5.5296099 | AU21: =AH16 -> 6.4027062 | AV21: =AN21-AP21 -> 1.0254625e+08 | AW21: =AO21-AQ21 -> 83084123
B22: Year 13 | C22: =IF(RAND() < (10-5)/(14-5), 5 + SQRT(RAND() * (10-5) * (14-5)), 14 - SQRT((1-RAND()) * (14-10) * (14-5))) -> 9.3075242 | F22: Year 13 | G22: =_xlfn.NORM.INV(RAND(),1900000,250000) -> 2147057.2 | I22: Year 13 | J22: =J21 * _xlfn.NORM.INV(RAND(),$J$7,$K$7) -> 193.5206 | M22: Year 11 | N22: =C20*$N$7 -> 7.6698654 | O22: =C20*$O$7 -> 8.8808968 | Q22: Year 11 | R22: =_xlfn.LOGNORM.INV(RAND(),$R$7,$R$8) -> 1856223 | T22: Year 11 | U22: =_xlfn.LOGNORM.INV(RAND(),$U$7,$U$8) -> 2672303.8 | W22: Year 17 | X22: =IF(RAND() < 0.05, 1, 0) -> 1 | Z22: Year 16 | AA22: =IF(X21=1, -LN(RAND()) / 5, 0) -> 0 | AC22: =IF(X21=1, -LN(RAND()) / 10, 0) -> 0 | AE22: Year 16 | AF22: =N27 * (1 - AA22) -> 7.4736064 | AH22: =O27 * (1 - AC22) -> 8.6536496 | AM22: Year 11 | AN22: =MIN(AF17,J20) * G20 * 20 -> 2.8042394e+08 | AO22: =MIN(AH17,J20) * G20 * 20 -> 3.247014e+08 | AP22: =$N$10 + R22 * 20 -> 1.0712446e+08 | AQ22: =$O$10 + U22 * 20 -> 1.6344608e+08 | AT22: =AF17 -> 7.6698654 | AU22: =AH17 -> 8.8808968 | AV22: =AN22-AP22 -> 1.7329948e+08 | AW22: =AO22-AQ22 -> 1.6125533e+08
B23: Year 14 | C23: =IF(RAND() < (10-5)/(14-5), 5 + SQRT(RAND() * (10-5) * (14-5)), 14 - SQRT((1-RAND()) * (14-10) * (14-5))) -> 6.6777556 | F23: Year 14 | G23: =_xlfn.NORM.INV(RAND(),1900000,250000) -> 1699265.1 | I23: Year 14 | J23: =J22 * _xlfn.NORM.INV(RAND(),$J$7,$K$7) -> 201.97498 | M23: Year 12 | N23: =C21*$N$7 -> 8.8388759 | O23: =C21*$O$7 -> 10.234488 | Q23: Year 12 | R23: =_xlfn.LOGNORM.INV(RAND(),$R$7,$R$8) -> 1566284.6 | T23: Year 12 | U23: =_xlfn.LOGNORM.INV(RAND(),$U$7,$U$8) -> 2597150.2 | W23: Year 18 | X23: =IF(RAND() < 0.05, 1, 0) -> 0 | Z23: Year 17 | AA23: =IF(X22=1, -LN(RAND()) / 5, 0) -> 0.39179413 | AC23: =IF(X22=1, -LN(RAND()) / 10, 0) -> 0.045419812 | AE23: Year 17 | AF23: =N28 * (1 - AA23) -> 4.5310586 | AH23: =O28 * (1 - AC23) -> 8.2343736 | AM23: Year 12 | AN23: =MIN(AF18,J21) * G21 * 20 -> 3.814801e+08 | AO23: =MIN(AH18,J21) * G21 * 20 -> 4.417138e+08 | AP23: =$N$10 + R23 * 20 -> 1.0132569e+08 | AQ23: =$O$10 + U23 * 20 -> 1.61943e+08 | AT23: =AF18 -> 8.8388759 | AU23: =AH18 -> 10.234488 | AV23: =AN23-AP23 -> 2.8015441e+08 | AW23: =AO23-AQ23 -> 2.797708e+08
B24: Year 15 | C24: =IF(RAND() < (10-5)/(14-5), 5 + SQRT(RAND() * (10-5) * (14-5)), 14 - SQRT((1-RAND()) * (14-10) * (14-5))) -> 11.394846 | F24: Year 15 | G24: =_xlfn.NORM.INV(RAND(),1900000,250000) -> 1660387.5 | I24: Year 15 | J24: =J23 * _xlfn.NORM.INV(RAND(),$J$7,$K$7) -> 212.44734 | M24: Year 13 | N24: =C22*$N$7 -> 8.842148 | O24: =C22*$O$7 -> 10.238277 | Q24: Year 13 | R24: =_xlfn.LOGNORM.INV(RAND(),$R$7,$R$8) -> 1383968.8 | T24: Year 13 | U24: =_xlfn.LOGNORM.INV(RAND(),$U$7,$U$8) -> 2585967.5 | W24: Year 19 | X24: =IF(RAND() < 0.05, 1, 0) -> 1 | Z24: Year 18 | AA24: =IF(X23=1, -LN(RAND()) / 5, 0) -> 0 | AC24: =IF(X23=1, -LN(RAND()) / 10, 0) -> 0 | AE24: Year 18 | AF24: =N29 * (1 - AA24) -> 9.9500616 | AH24: =O29 * (1 - AC24) -> 11.521124 | AM24: Year 13 | AN24: =MIN(AF19,J22) * G22 * 20 -> 3.7969194e+08 | AO24: =MIN(AH19,J22) * G22 * 20 -> 4.396433e+08 | AP24: =$N$10 + R24 * 20 -> 97679375 | AQ24: =$O$10 + U24 * 20 -> 1.6171935e+08 | AT24: =AF19 -> 8.842148 | AU24: =AH19 -> 10.238277 | AV24: =AN24-AP24 -> 2.8201257e+08 | AW24: =AO24-AQ24 -> 2.7792395e+08
B25: Year 16 | C25: =IF(RAND() < (10-5)/(14-5), 5 + SQRT(RAND() * (10-5) * (14-5)), 14 - SQRT((1-RAND()) * (14-10) * (14-5))) -> 7.8669542 | F25: Year 16 | G25: =_xlfn.NORM.INV(RAND(),1900000,250000) -> 1815007.6 | I25: Year 16 | J25: =J24 * _xlfn.NORM.INV(RAND(),$J$7,$K$7) -> 206.4997 | M25: Year 14 | N25: =C23*$N$7 -> 6.3438678 | O25: =C23*$O$7 -> 7.3455311 | Q25: Year 14 | R25: =_xlfn.LOGNORM.INV(RAND(),$R$7,$R$8) -> 1145436.9 | T25: Year 14 | U25: =_xlfn.LOGNORM.INV(RAND(),$U$7,$U$8) -> 2452234.6 | W25: Year 20 | X25: =IF(RAND() < 0.05, 1, 0) -> 1 | Z25: Year 19 | AA25: =IF(X24=1, -LN(RAND()) / 5, 0) -> 0.26801312 | AC25: =IF(X24=1, -LN(RAND()) / 10, 0) -> 0.02560492 | AE25: Year 19 | AF25: =N30 * (1 - AA25) -> 7.0281347 | AH25: =O30 * (1 - AC25) -> 10.832806 | AM25: Year 14 | AN25: =MIN(AF20,J23) * G23 * 20 -> 2.1559826e+08 | AO25: =MIN(AH20,J23) * G23 * 20 -> 2.4964009e+08 | AP25: =$N$10 + R25 * 20 -> 92908737 | AQ25: =$O$10 + U25 * 20 -> 1.5904469e+08 | AT25: =AF20 -> 6.3438678 | AU25: =AH20 -> 7.3455311 | AV25: =AN25-AP25 -> 1.2268952e+08 | AW25: =AO25-AQ25 -> 90595402
B26: Year 17 | C26: =IF(RAND() < (10-5)/(14-5), 5 + SQRT(RAND() * (10-5) * (14-5)), 14 - SQRT((1-RAND()) * (14-10) * (14-5))) -> 7.8419752 | F26: Year 17 | G26: =_xlfn.NORM.INV(RAND(),1900000,250000) -> 1808349.9 | I26: Year 17 | J26: =J25 * _xlfn.NORM.INV(RAND(),$J$7,$K$7) -> 207.71051 | M26: Year 15 | N26: =C24*$N$7 -> 10.825104 | O26: =C24*$O$7 -> 12.534331 | Q26: Year 15 | R26: =_xlfn.LOGNORM.INV(RAND(),$R$7,$R$8) -> 1382228.3 | T26: Year 15 | U26: =_xlfn.LOGNORM.INV(RAND(),$U$7,$U$8) -> 2454101.9 | Z26: Year 20 | AA26: =IF(X25=1, -LN(RAND()) / 5, 0) -> 0.02276309 | AC26: =IF(X25=1, -LN(RAND()) / 10, 0) -> 0.21537459 | AE26: Year 20 | AF26: =N31 * (1 - AA26) -> 11.566949 | AH26: =O31 * (1 - AC26) -> 10.753514 | AM26: Year 15 | AN26: =MIN(AF21,J24) * G24 * 20 -> 3.5947733e+08 | AO26: =MIN(AH21,J24) * G24 * 20 -> 4.1623691e+08 | AP26: =$N$10 + R26 * 20 -> 97644567 | AQ26: =$O$10 + U26 * 20 -> 1.5908204e+08 | AT26: =AF21 -> 10.825104 | AU26: =AH21 -> 12.534331 | AV26: =AN26-AP26 -> 2.6183277e+08 | AW26: =AO26-AQ26 -> 2.5715488e+08
B27: Year 18 | C27: =IF(RAND() < (10-5)/(14-5), 5 + SQRT(RAND() * (10-5) * (14-5)), 14 - SQRT((1-RAND()) * (14-10) * (14-5))) -> 10.473749 | F27: Year 18 | G27: =_xlfn.NORM.INV(RAND(),1900000,250000) -> 2041928.6 | I27: Year 18 | J27: =J26 * _xlfn.NORM.INV(RAND(),$J$7,$K$7) -> 208.2363 | M27: Year 16 | N27: =C25*$N$7 -> 7.4736064 | O27: =C25*$O$7 -> 8.6536496 | Q27: Year 16 | R27: =_xlfn.LOGNORM.INV(RAND(),$R$7,$R$8) -> 1738544.6 | T27: Year 16 | U27: =_xlfn.LOGNORM.INV(RAND(),$U$7,$U$8) -> 2412621.3 | AM27: Year 16 | AN27: =MIN(AF22,J25) * G25 * 20 -> 2.7129305e+08 | AO27: =MIN(AH22,J25) * G25 * 20 -> 3.1412879e+08 | AP27: =$N$10 + R27 * 20 -> 1.0477089e+08 | AQ27: =$O$10 + U27 * 20 -> 1.5825243e+08 | AT27: =AF22 -> 7.4736064 | AU27: =AH22 -> 8.6536496 | AV27: =AN27-AP27 -> 1.6652215e+08 | AW27: =AO27-AQ27 -> 1.5587636e+08
B28: Year 19 | C28: =IF(RAND() < (10-5)/(14-5), 5 + SQRT(RAND() * (10-5) * (14-5)), 14 - SQRT((1-RAND()) * (14-10) * (14-5))) -> 10.106789 | F28: Year 19 | G28: =_xlfn.NORM.INV(RAND(),1900000,250000) -> 1577094.5 | I28: Year 19 | J28: =J27 * _xlfn.NORM.INV(RAND(),$J$7,$K$7) -> 199.60567 | M28: Year 17 | N28: =C26*$N$7 -> 7.4498765 | O28: =C26*$O$7 -> 8.6261728 | Q28: Year 17 | R28: =_xlfn.LOGNORM.INV(RAND(),$R$7,$R$8) -> 1908062.9 | T28: Year 17 | U28: =_xlfn.LOGNORM.INV(RAND(),$U$7,$U$8) -> 2361869.4 | AM28: Year 17 | AN28: =MIN(AF23,J26) * G26 * 20 -> 1.6387479e+08 | AO28: =MIN(AH23,J26) * G26 * 20 -> 2.9781258e+08 | AP28: =$N$10 + R28 * 20 -> 1.0816126e+08 | AQ28: =$O$10 + U28 * 20 -> 1.5723739e+08 | AT28: =AF23 -> 4.5310586 | AU28: =AH23 -> 8.2343736 | AV28: =AN28-AP28 -> 55713529 | AW28: =AO28-AQ28 -> 1.4057519e+08
B29: Year 20 | C29: =IF(RAND() < (10-5)/(14-5), 5 + SQRT(RAND() * (10-5) * (14-5)), 14 - SQRT((1-RAND()) * (14-10) * (14-5))) -> 12.459349 | F29: Year 20 | G29: =_xlfn.NORM.INV(RAND(),1900000,250000) -> 1941054.7 | I29: Year 20 | J29: =J28 * _xlfn.NORM.INV(RAND(),$J$7,$K$7) -> 203.11941 | M29: Year 18 | N29: =C27*$N$7 -> 9.9500616 | O29: =C27*$O$7 -> 11.521124 | Q29: Year 18 | R29: =_xlfn.LOGNORM.INV(RAND(),$R$7,$R$8) -> 1622966.9 | T29: Year 18 | U29: =_xlfn.LOGNORM.INV(RAND(),$U$7,$U$8) -> 2193785.9 | AM29: Year 18 | AN29: =MIN(AF24,J27) * G27 * 20 -> 4.0634632e+08 | AO29: =MIN(AH24,J27) * G27 * 20 -> 4.7050626e+08 | AP29: =$N$10 + R29 * 20 -> 1.0245934e+08 | AQ29: =$O$10 + U29 * 20 -> 1.5387572e+08 | AT29: =AF24 -> 9.9500616 | AU29: =AH24 -> 11.521124 | AV29: =AN29-AP29 -> 3.0388698e+08 | AW29: =AO29-AQ29 -> 3.1663054e+08
M30: Year 19 | N30: =C28*$N$7 -> 9.6014491 | O30: =C28*$O$7 -> 11.117467 | Q30: Year 19 | R30: =_xlfn.LOGNORM.INV(RAND(),$R$7,$R$8) -> 1568781.9 | T30: Year 19 | U30: =_xlfn.LOGNORM.INV(RAND(),$U$7,$U$8) -> 2454301.5 | AM30: Year 19 | AN30: =MIN(AF25,J28) * G28 * 20 -> 2.2168065e+08 | AO30: =MIN(AH25,J28) * G28 * 20 -> 3.4168715e+08 | AP30: =$N$10 + R30 * 20 -> 1.0137564e+08 | AQ30: =$O$10 + U30 * 20 -> 1.5908603e+08 | AT30: =AF25 -> 7.0281347 | AU30: =AH25 -> 10.832806 | AV30: =AN30-AP30 -> 1.2030501e+08 | AW30: =AO30-AQ30 -> 1.8260112e+08
M31: Year 20 | N31: =C29*$N$7 -> 11.836381 | O31: =C29*$O$7 -> 13.705284 | Q31: Year 20 | R31: =_xlfn.LOGNORM.INV(RAND(),$R$7,$R$8) -> 1949127.4 | T31: Year 20 | U31: =_xlfn.LOGNORM.INV(RAND(),$U$7,$U$8) -> 2878820.2 | AM31: Year 20 | AN31: =MIN(AF26,J29) * G29 * 20 -> 4.490416e+08 | AO31: =MIN(AH26,J29) * G29 * 20 -> 4.1746317e+08 | AP31: =$N$10 + R31 * 20 -> 1.0898255e+08 | AQ31: =$O$10 + U31 * 20 -> 1.675764e+08 | AT31: =AF26 -> 11.566949 | AU31: =AH26 -> 10.753514 | AV31: =AN31-AP31 -> 3.4005905e+08 | AW31: =AO31-AQ31 -> 2.4988676e+08

Sheet Varity C - Syrah
C2: Varity C - Syrah | M2: Farming tecniques: | P2: Material costs per hectar | V2: Disese occurance | Y2: Exponential distribution | AE2: Adjusting yield to deases risk
M3: Traditional farming | N3: Modern farming | P3: Traditinal farming | S3: Modern farming | V3: 5 % probability of occuring each year | Y3: Traditonal | AB3: Modern | AE3: Traditional | AG3: Modern | AL3: Annual revenue | AN3: Costs | AP3: Disease events | AR3: Yield | AT3: Profit per year
C4: Annual yield | D4: Triangular distribution | F4: Price per ton | G4: Normal distribution | I4: Annual demand | J4: Normal distribution | L4: Annual fixed cost per hectar | M4: 3500000 | N4: 5500000 | P4: Mean | Q4: CLP 1 900 000,00 | S4: Mean | T4: 3000000 | V4: 0 if it dosent occure, 1 if it does | Y4: Lambda | Z4: 5 | AB4: 10
L5: Effect on the annual yield in percentage | M5: 0.95 | N5: 1.1 | P5: STD | Q5: CLP 250 000,00 | S5: STD | T5: 220000 | Y5: Average | Z5: 0.1 | AB5: 0.2
C6: Min | D6: 4 | F6: Mean | G6: 2500000 | I6: Mean | J6: 1.03 | L6: Total hectar per year | M6: 20 | N6: 20
C7: Mostly | D7: 8 | F7: STD | G7: 175000 | I7: STD | J7: 0.03 | P7: Scaled mean | Q7: 14.45 | S7: Scaled mean | T7: 14.86
C8: Max | D8: 12 | I8: Inn ton | L8: Fixed cost per year | M8: =M4*M6 -> 70000000 | N8: =N4*N6 -> 110000000 | P8: Scaled STD | Q8: 0.131 | S8: Scaled STD | T8: 0.073
M9: Adjusted yield traditional | N9: Adjusted yield modern | AL9: Traditional | AM9: Modern | AN9: Traditonal | AO9: Modern | AP9: Traditional | AQ9: Modern | AR9: Traditional | AS9: Modern | AT9: Traditonal | AU9: Modern
C10: Year 1 | D10: =IF(RAND() < (8-4)/(12-4), 4 + SQRT(RAND() * (8-4) * (12-4)), 12 - SQRT((1-RAND()) * (12-8) * (12-4))) -> 6.7325968 | F10: Year 1 | G10: =_xlfn.NORM.INV(RAND(),2500000,175000) -> 2527907.8 | I10: Year 1 | J10: 130 | L10: Year 1 | M10: =D10*$M$5 -> 6.395967 | N10: =D10 * $N$5 -> 7.4058565 | P10: Year 1 | Q10: =_xlfn.LOGNORM.INV(RAND(),$Q$7,$Q$8) -> 1993939.8 | S10: Year 1 | T10: =_xlfn.LOGNORM.INV(RAND(),$T$7,$T$8) -> 2762103.7 | V10: Year 1 | W10: =IF(RAND() < 0.05, 1, 0) -> 0 | Y10: Year 1 | Z10: =IF(W10=1, -LN(RAND()) / 5, 0) -> 0 | AB10: =IF(W10=1, -LN(RAND()) / 10, 0) -> 0 | AD10: Year 1 | AE10: =M10 * (1 - Z10) -> 6.395967 | AG10: =N10 * (1 - AB10) -> 7.4058565 | AK10: Year 1 | AL10: =MIN(AE10,J10) * G10 * 20 -> 3.2336829e+08 | AM10: =MIN(AG10,J10) * G10 * 20 -> 3.7442644e+08 | AN10: =$M$8 + Q10 * 20 -> 1.098788e+08 | AO10: =$N$8 + T10 * 20 -> 1.6524207e+08 | AP10: =SUM(W10:W29) -> 0 | AQ10: =SUM(W10:W29) -> 0 | AR10: =AE10 -> 6.395967 | AS10: =AG10 -> 7.4058565 | AT10: =AL10-AN10 -> 2.134895e+08 | AU10: =AM10-AO10 -> 2.0918437e+08
C11: Year 2 | D11: =IF(RAND() < (8-4)/(12-4), 4 + SQRT(RAND() * (8-4) * (12-4)), 12 - SQRT((1-RAND()) * (12-8) * (12-4))) -> 9.2516071 | F11: Year 2 | G11: =_xlfn.NORM.INV(RAND(),2500000,175000) -> 2740966.2 | I11: Year 2 | J11: =J10 * _xlfn.NORM.INV(RAND(),$J$6,$J$7) -> 131.09797 | L11: Year 2 | M11: =D11*$M$5 -> 8.7890268 | N11: =D11 * $N$5 -> 10.176768 | P11: Year 2 | Q11: =_xlfn.LOGNORM.INV(RAND(),$Q$7,$Q$8) -> 2083451.4 | S11: Year 2 | T11: =_xlfn.LOGNORM.INV(RAND(),$T$7,$T$8) -> 2947383.2 | V11: Year 2 | W11: =IF(RAND() < 0.05, 1, 0) -> 0 | Y11: Year 2 | Z11: =IF(W11=1, -LN(RAND()) / 5, 0) -> 0 | AB11: =IF(W11=1, -LN(RAND()) / 10, 0) -> 0 | AD11: Year 2 | AE11: =M11 * (1 - Z11) -> 8.7890268 | AG11: =N11 * (1 - AB11) -> 10.176768 | AK11: Year 2 | AL11: =MIN(AE11,J11) * G11 * 20 -> 4.8180851e+08 | AM11: =MIN(AG11,J11) * G11 * 20 -> 5.5788354e+08 | AN11: =$M$8 + Q11 * 20 -> 1.1166903e+08 | AO11: =$N$8 + T11 * 20 -> 1.6894766e+08 | AR11: =AE11 -> 8.7890268 | AS11: =AG11 -> 10.176768 | AT11: =AL11-AN11 -> 3.7013948e+08 | AU11: =AM11-AO11 -> 3.8893587e+08
C12: Year 3 | D12: =IF(RAND() < (8-4)/(12-4), 4 + SQRT(RAND() * (8-4) * (12-4)), 12 - SQRT((1-RAND()) * (12-8) * (12-4))) -> 4.9212431 | F12: Year 3 | G12: =_xlfn.NORM.INV(RAND(),2500000,175000) -> 2883654.8 | I12: Year 3 | J12: =J11 * _xlfn.NORM.INV(RAND(),$J$6,$J$7) -> 137.92243 | L12: Year 3 | M12: =D12*$M$5 -> 4.675181 | N12: =D12 * $N$5 -> 5.4133674 | P12: Year 3 | Q12: =_xlfn.LOGNORM.INV(RAND(),$Q$7,$Q$8) -> 2315672 | S12: Year 3 | T12: =_xlfn.LOGNORM.INV(RAND(),$T$7,$T$8) -> 2772103.9 | V12: Year 3 | W12: =IF(RAND() < 0.05, 1, 0) -> 0 | Y12: Year 3 | Z12: =IF(W12=1, -LN(RAND()) / 5, 0) -> 0 | AB12: =IF(W12=1, -LN(RAND()) / 10, 0) -> 0 | AD12: Year 3 | AE12: =M12 * (1 - Z12) -> 4.675181 | AG12: =N12 * (1 - AB12) -> 5.4133674 | AK12: Year 3 | AL12: =MIN(AE12,J12) * G12 * 20 -> 2.6963216e+08 | AM12: =MIN(AG12,J12) * G12 * 20 -> 3.1220565e+08 | AN12: =$M$8 + Q12 * 20 -> 1.1631344e+08 | AO12: =$N$8 + T12 * 20 -> 1.6544208e+08 | AR12: =AE12 -> 4.675181 | AS12: =AG12 -> 5.4133674 | AT12: =AL12-AN12 -> 1.5331872e+08 | AU12: =AM12-AO12 -> 1.4676358e+08
C13: Year 4 | D13: =IF(RAND() < (8-4)/(12-4), 4 + SQRT(RAND() * (8-4) * (12-4)), 12 - SQRT((1-RAND()) * (12-8) * (12-4))) -> 7.787607 | F13: Year 4 | G13: =_xlfn.NORM.INV(RAND(),2500000,175000) -> 2474088.8 | I13: Year 4 | J13: =J12 * _xlfn.NORM.INV(RAND(),$J$6,$J$7) -> 140.32707 | L13: Year 4 | M13: =D13*$M$5 -> 7.3982266 | N13: =D13 * $N$5 -> 8.5663677 | P13: Year 4 | Q13: =_xlfn.LOGNORM.INV(RAND(),$Q$7,$Q$8) -> 2009570.1 | S13: Year 4 | T13: =_xlfn.LOGNORM.INV(RAND(),$T$7,$T$8) -> 2548743.3 | V13: Year 4 | W13: =IF(RAND() < 0.05, 1, 0) -> 0 | Y13: Year 4 | Z13: =IF(W13=1, -LN(RAND()) / 5, 0) -> 0 | AB13: =IF(W13=1, -LN(RAND()) / 10, 0) -> 0 | AD13: Year 4 | AE13: =M13 * (1 - Z13) -> 7.3982266 | AG13: =N13 * (1 - AB13) -> 8.5663677 | AK13: Year 4 | AL13: =MIN(AE13,J13) * G13 * 20 -> 3.660774e+08 | AM13: =MIN(AG13,J13) * G13 * 20 -> 4.2387909e+08 | AN13: =$M$8 + Q13 * 20 -> 1.101914e+08 | AO13: =$N$8 + T13 * 20 -> 1.6097487e+08 | AR13: =AE13 -> 7.3982266 | AS13: =AG13 -> 8.5663677 | AT13: =AL13-AN13 -> 2.5588599e+08 | AU13: =AM13-AO13 -> 2.6290423e+08
C14: Year 5 | D14: =IF(RAND() < (8-4)/(12-4), 4 + SQRT(RAND() * (8-4) * (12-4)), 12 - SQRT((1-RAND()) * (12-8) * (12-4))) -> 11.168325 | F14: Year 5 | G14: =_xlfn.NORM.INV(RAND(),2500000,175000) -> 2683569.6 | I14: Year 5 | J14: =J13 * _xlfn.NORM.INV(RAND(),$J$6,$J$7) -> 142.90596 | L14: Year 5 | M14: =D14*$M$5 -> 10.609908 | N14: =D14 * $N$5 -> 12.285157 | P14: Year 5 | Q14: =_xlfn.LOGNORM.INV(RAND(),$Q$7,$Q$8) -> 1713561.9 | S14: Year 5 | T14: =_xlfn.LOGNORM.INV(RAND(),$T$7,$T$8) -> 3068062.7 | V14: Year 5 | W14: =IF(RAND() < 0.05, 1, 0) -> 0 | Y14: Year 5 | Z14: =IF(W14=1, -LN(RAND()) / 5, 0) -> 0 | AB14: =IF(W14=1, -LN(RAND()) / 10, 0) -> 0 | AD14: Year 5 | AE14: =M14 * (1 - Z14) -> 10.609908 | AG14: =N14 * (1 - AB14) -> 12.285157 | AK14: Year 5 | AL14: =MIN(AE14,J14) * G14 * 20 -> 5.6944855e+08 | AM14: =MIN(AG14,J14) * G14 * 20 -> 6.5936148e+08 | AN14: =$M$8 + Q14 * 20 -> 1.0427124e+08 | AO14: =$N$8 + T14 * 20 -> 1.7136125e+08 | AR14: =AE14 -> 10.609908 | AS14: =AG14 -> 12.285157 | AT14: =AL14-AN14 -> 4.6517732e+08 | AU14: =AM14-AO14 -> 4.8800023e+08
C15: Year 6 | D15: =IF(RAND() < (8-4)/(12-4), 4 + SQRT(RAND() * (8-4) * (12-4)), 12 - SQRT((1-RAND()) * (12-8) * (12-4))) -> 9.2852397 | F15: Year 6 | G15: =_xlfn.NORM.INV(RAND(),2500000,175000) -> 2324884.8 | I15: Year 6 | J15: =J14 * _xlfn.NORM.INV(RAND(),$J$6,$J$7) -> 146.19579 | L15: Year 6 | M15: =D15*$M$5 -> 8.8209777 | N15: =D15 * $N$5 -> 10.213764 | P15: Year 6 | Q15: =_xlfn.LOGNORM.INV(RAND(),$Q$7,$Q$8) -> 1835594.2 | S15: Year 6 | T15: =_xlfn.LOGNORM.INV(RAND(),$T$7,$T$8) -> 2933705.2 | V15: Year 6 | W15: =IF(RAND() < 0.05, 1, 0) -> 0 | Y15: Year 6 | Z15: =IF(W15=1, -LN(RAND()) / 5, 0) -> 0 | AB15: =IF(W15=1, -LN(RAND()) / 10, 0) -> 0 | AD15: Year 6 | AE15: =M15 * (1 - Z15) -> 8.8209777 | AG15: =N15 * (1 - AB15) -> 10.213764 | AK15: Year 6 | AL15: =MIN(AE15,J15) * G15 * 20 -> 4.1015515e+08 | AM15: =MIN(AG15,J15) * G15 * 20 -> 4.7491649e+08 | AN15: =$M$8 + Q15 * 20 -> 1.0671188e+08 | AO15: =$N$8 + T15 * 20 -> 1.686741e+08 | AR15: =AE15 -> 8.8209777 | AS15: =AG15 -> 10.213764 | AT15: =AL15-AN15 -> 3.0344326e+08 | AU15: =AM15-AO15 -> 3.0624238e+08
C16: Year 7 | D16: =IF(RAND() < (8-4)/(12-4), 4 + SQRT(RAND() * (8-4) * (12-4)), 12 - SQRT((1-RAND()) * (12-8) * (12-4))) -> 5.978401 | F16: Year 7 | G16: =_xlfn.NORM.INV(RAND(),2500000,175000) -> 2481870.6 | I16: Year 7 | J16: =J15 * _xlfn.NORM.INV(RAND(),$J$6,$J$7) -> 155.85328 | L16: Year 7 | M16: =D16*$M$5 -> 5.679481 | N16: =D16 * $N$5 -> 6.5762412 | P16: Year 7 | Q16: =_xlfn.LOGNORM.INV(RAND(),$Q$7,$Q$8) -> 2115808.4 | S16: Year 7 | T16: =_xlfn.LOGNORM.INV(RAND(),$T$7,$T$8) -> 2871340.6 | V16: Year 7 | W16: =IF(RAND() < 0.05, 1, 0) -> 0 | Y16: Year 7 | Z16: =IF(W16=1, -LN(RAND()) / 5, 0) -> 0 | AB16: =IF(W16=1, -LN(RAND()) / 10, 0) -> 0 | AD16: Year 7 | AE16: =M16 * (1 - Z16) -> 5.679481 | AG16: =N16 * (1 - AB16) -> 6.5762412 | AK16: Year 7 | AL16: =MIN(AE16,J16) * G16 * 20 -> 2.8191474e+08 | AM16: =MIN(AG16,J16) * G16 * 20 -> 3.2642759e+08 | AN16: =$M$8 + Q16 * 20 -> 1.1231617e+08 | AO16: =$N$8 + T16 * 20 -> 1.6742681e+08 | AR16: =AE16 -> 5.679481 | AS16: =AG16 -> 6.5762412 | AT16: =AL16-AN16 -> 1.6959857e+08 | AU16: =AM16-AO16 -> 1.5900078e+08
C17: Year 8 | D17: =IF(RAND() < (8-4)/(12-4), 4 + SQRT(RAND() * (8-4) * (12-4)), 12 - SQRT((1-RAND()) * (12-8) * (12-4))) -> 9.2968132 | F17: Year 8 | G17: =_xlfn.NORM.INV(RAND(),2500000,175000) -> 2530025.8 | I17: Year 8 | J17: =J16 * _xlfn.NORM.INV(RAND(),$J$6,$J$7) -> 154.14298 | L17: Year 8 | M17: =D17*$M$5 -> 8.8319726 | N17: =D17 * $N$5 -> 10.226495 | P17: Year 8 | Q17: =_xlfn.LOGNORM.INV(RAND(),$Q$7,$Q$8) -> 1591958.2 | S17: Year 8 | T17: =_xlfn.LOGNORM.INV(RAND(),$T$7,$T$8) -> 2932476.6 | V17: Year 8 | W17: =IF(RAND() < 0.05, 1, 0) -> 0 | Y17: Year 8 | Z17: =IF(W17=1, -LN(RAND()) / 5, 0) -> 0 | AB17: =IF(W17=1, -LN(RAND()) / 10, 0) -> 0 | AD17: Year 8 | AE17: =M17 * (1 - Z17) -> 8.8319726 | AG17: =N17 * (1 - AB17) -> 10.226495 | AK17: Year 8 | AL17: =MIN(AE17,J17) * G17 * 20 -> 4.4690237e+08 | AM17: =MIN(AG17,J17) * G17 * 20 -> 5.174659e+08 | AN17: =$M$8 + Q17 * 20 -> 1.0183916e+08 | AO17: =$N$8 + T17 * 20 -> 1.6864953e+08 | AR17: =AE17 -> 8.8319726 | AS17: =AG17 -> 10.226495 | AT17: =AL17-AN17 -> 3.450632e+08 | AU17: =AM17-AO17 -> 3.4881637e+08
C18: Year 9 | D18: =IF(RAND() < (8-4)/(12-4), 4 + SQRT(RAND() * (8-4) * (12-4)), 12 - SQRT((1-RAND()) * (12-8) * (12-4))) -> 5.1190926 | F18: Year 9 | G18: =_xlfn.NORM.INV(RAND(),2500000,175000) -> 2250844.2 | I18: Year 9 | J18: =J17 * _xlfn.NORM.INV(RAND(),$J$6,$J$7) -> 160.82551 | L18: Year 9 | M18: =D18*$M$5 -> 4.863138 | N18: =D18 * $N$5 -> 5.6310019 | P18: Year 9 | Q18: =_xlfn.LOGNORM.INV(RAND(),$Q$7,$Q$8) -> 1836179.2 | S18: Year 9 | T18: =_xlfn.LOGNORM.INV(RAND(),$T$7,$T$8) -> 2662711.2 | V18: Year 9 | W18: =IF(RAND() < 0.05, 1, 0) -> 0 | Y18: Year 9 | Z18: =IF(W18=1, -LN(RAND()) / 5, 0) -> 0 | AB18: =IF(W18=1, -LN(RAND()) / 10, 0) -> 0 | AD18: Year 9 | AE18: =M18 * (1 - Z18) -> 4.863138 | AG18: =N18 * (1 - AB18) -> 5.6310019 | AK18: Year 9 | AL18: =MIN(AE18,J18) * G18 * 20 -> 2.1892331e+08 | AM18: =MIN(AG18,J18) * G18 * 20 -> 2.5349015e+08 | AN18: =$M$8 + Q18 * 20 -> 1.0672358e+08 | AO18: =$N$8 + T18 * 20 -> 1.6325422e+08 | AR18: =AE18 -> 4.863138 | AS18: =AG18 -> 5.6310019 | AT18: =AL18-AN18 -> 1.1219973e+08 | AU18: =AM18-AO18 -> 90235929
C19: Year 10 | D19: =IF(RAND() < (8-4)/(12-4), 4 + SQRT(RAND() * (8-4) * (12-4)), 12 - SQRT((1-RAND()) * (12-8) * (12-4))) -> 7.3880108 | F19: Year 10 | G19: =_xlfn.NORM.INV(RAND(),2500000,175000) -> 2529418.3 | I19: Year 10 | J19: =J18 * _xlfn.NORM.INV(RAND(),$J$6,$J$7) -> 170.34201 | L19: Year 10 | M19: =D19*$M$5 -> 7.0186102 | N19: =D19 * $N$5 -> 8.1268119 | P19: Year 10 | Q19: =_xlfn.LOGNORM.INV(RAND(),$Q$7,$Q$8) -> 1765403.7 | S19: Year 10 | T19: =_xlfn.LOGNORM.INV(RAND(),$T$7,$T$8) -> 2553323.5 | V19: Year 10 | W19: =IF(RAND() < 0.05, 1, 0) -> 0 | Y19: Year 10 | Z19: =IF(W19=1, -LN(RAND()) / 5, 0) -> 0 | AB19: =IF(W19=1, -LN(RAND()) / 10, 0) -> 0 | AD19: Year 10 | AE19: =M19 * (1 - Z19) -> 7.0186102 | AG19: =N19 * (1 - AB19) -> 8.1268119 | AK19: Year 10 | AL19: =MIN(AE19,J19) * G19 * 20 -> 3.5506003e+08 | AM19: =MIN(AG19,J19) * G19 * 20 -> 4.1112214e+08 | AN19: =$M$8 + Q19 * 20 -> 1.0530807e+08 | AO19: =$N$8 + T19 * 20 -> 1.6106647e+08 | AR19: =AE19 -> 7.0186102 | AS19: =AG19 -> 8.1268119 | AT19: =AL19-AN19 -> 2.4975195e+08 | AU19: =AM19-AO19 -> 2.5005567e+08
C20: Year 11 | D20: =IF(RAND() < (8-4)/(12-4), 4 + SQRT(RAND() * (8-4) * (12-4)), 12 - SQRT((1-RAND()) * (12-8) * (12-4))) -> 6.4608188 | F20: Year 11 | G20: =_xlfn.NORM.INV(RAND(),2500000,175000) -> 2394209.5 | I20: Year 11 | J20: =J19 * _xlfn.NORM.INV(RAND(),$J$6,$J$7) -> 180.53459 | L20: Year 11 | M20: =D20*$M$5 -> 6.1377779 | N20: =D20 * $N$5 -> 7.1069007 | P20: Year 11 | Q20: =_xlfn.LOGNORM.INV(RAND(),$Q$7,$Q$8) -> 1574191.1 | S20: Year 11 | T20: =_xlfn.LOGNORM.INV(RAND(),$T$7,$T$8) -> 2704830.9 | V20: Year 11 | W20: =IF(RAND() < 0.05, 1, 0) -> 0 | Y20: Year 11 | Z20: =IF(W20=1, -LN(RAND()) / 5, 0) -> 0 | AB20: =IF(W20=1, -LN(RAND()) / 10, 0) -> 0 | AD20: Year 11 | AE20: =M20 * (1 - Z20) -> 6.1377779 | AG20: =N20 * (1 - AB20) -> 7.1069007 | AK20: Year 11 | AL20: =MIN(AE20,J20) * G20 * 20 -> 2.9390252e+08 | AM20: =MIN(AG20,J20) * G20 * 20 -> 3.4030818e+08 | AN20: =$M$8 + Q20 * 20 -> 1.0148382e+08 | AO20: =$N$8 + T20 * 20 -> 1.6409662e+08 | AR20: =AE20 -> 6.1377779 | AS20: =AG20 -> 7.1069007 | AT20: =AL20-AN20 -> 1.924187e+08 | AU20: =AM20-AO20 -> 1.7621157e+08
C21: Year 12 | D21: =IF(RAND() < (8-4)/(12-4), 4 + SQRT(RAND() * (8-4) * (12-4)), 12 - SQRT((1-RAND()) * (12-8) * (12-4))) -> 8.4912178 | F21: Year 12 | G21: =_xlfn.NORM.INV(RAND(),2500000,175000) -> 2516223.6 | I21: Year 12 | J21: =J20 * _xlfn.NORM.INV(RAND(),$J$6,$J$7) -> 182.6781 | L21: Year 12 | M21: =D21*$M$5 -> 8.066657 | N21: =D21 * $N$5 -> 9.3403396 | P21: Year 12 | Q21: =_xlfn.LOGNORM.INV(RAND(),$Q$7,$Q$8) -> 2284994.5 | S21: Year 12 | T21: =_xlfn.LOGNORM.INV(RAND(),$T$7,$T$8) -> 2713118.5 | V21: Year 12 | W21: =IF(RAND() < 0.05, 1, 0) -> 0 | Y21: Year 12 | Z21: =IF(W21=1, -LN(RAND()) / 5, 0) -> 0 | AB21: =IF(W21=1, -LN(RAND()) / 10, 0) -> 0 | AD21: Year 12 | AE21: =M21 * (1 - Z21) -> 8.066657 | AG21: =N21 * (1 - AB21) -> 9.3403396 | AK21: Year 12 | AL21: =MIN(AE21,J21) * G21 * 20 -> 4.0595026e+08 | AM21: =MIN(AG21,J21) * G21 * 20 -> 4.7004767e+08 | AN21: =$M$8 + Q21 * 20 -> 1.1569989e+08 | AO21: =$N$8 + T21 * 20 -> 1.6426237e+08 | AR21: =AE21 -> 8.066657 | AS21: =AG21 -> 9.3403396 | AT21: =AL21-AN21 -> 2.9025037e+08 | AU21: =AM21-AO21 -> 3.0578529e+08
C22: Year 13 | D22: =IF(RAND() < (8-4)/(12-4), 4 + SQRT(RAND() * (8-4) * (12-4)), 12 - SQRT((1-RAND()) * (12-8) * (12-4))) -> 7.0993892 | F22: Year 13 | G22: =_xlfn.NORM.INV(RAND(),2500000,175000) -> 2400632.5 | I22: Year 13 | J22: =J21 * _xlfn.NORM.INV(RAND(),$J$6,$J$7) -> 191.02882 | L22: Year 13 | M22: =D22*$M$5 -> 6.7444198 | N22: =D22 * $N$5 -> 7.8093282 | P22: Year 13 | Q22: =_xlfn.LOGNORM.INV(RAND(),$Q$7,$Q$8) -> 1279021.5 | S22: Year 13 | T22: =_xlfn.LOGNORM.INV(RAND(),$T$7,$T$8) -> 2784113.6 | V22: Year 13 | W22: =IF(RAND() < 0.05, 1, 0) -> 0 | Y22: Year 13 | Z22: =IF(W22=1, -LN(RAND()) / 5, 0) -> 0 | AB22: =IF(W22=1, -LN(RAND()) / 10, 0) -> 0 | AD22: Year 13 | AE22: =M22 * (1 - Z22) -> 6.7444198 | AG22: =N22 * (1 - AB22) -> 7.8093282 | AK22: Year 13 | AL22: =MIN(AE22,J22) * G22 * 20 -> 3.2381747e+08 | AM22: =MIN(AG22,J22) * G22 * 20 -> 3.7494654e+08 | AN22: =$M$8 + Q22 * 20 -> 95580430 | AO22: =$N$8 + T22 * 20 -> 1.6568227e+08 | AR22: =AE22 -> 6.7444198 | AS22: =AG22 -> 7.8093282 | AT22: =AL22-AN22 -> 2.2823704e+08 | AU22: =AM22-AO22 -> 2.0926427e+08
... C29: Year 20 | D29: =IF(RAND() < (8-4)/(12-4), 4 + SQRT(RAND() * (8-4) * (12-4)), 12 - SQRT((1-RAND()) * (12-8) * (12-4))) -> 7.4955676 | F29: Year 20 | G29: =_xlfn.NORM.INV(RAND(),2500000,175000) -> 2380402 | I29: Year 20 | J29: =J28 * _xlfn.NORM.INV(RAND(),$J$6,$J$7) -> 252.88883 | L29: Year 20 | M29: =D29*$M$5 -> 7.1207892 | N29: =D29 * $N$5 -> 8.2451244 | P29: Year 20 | Q29: =_xlfn.LOGNORM.INV(RAND(),$Q$7,$Q$8) -> 1895968.3 | S29: Year 20 | T29: =_xlfn.LOGNORM.INV(RAND(),$T$7,$T$8) -> 2695427.2 | V29: Year 20 | W29: =IF(RAND() < 0.05, 1, 0) -> 0 | Y29: Year 20 | Z29: =IF(W29=1, -LN(RAND()) / 5, 0) -> 0 | AB29: =IF(W29=1, -LN(RAND()) / 10, 0) -> 0 | AD29: Year 20 | AE29: =M29 * (1 - Z29) -> 7.1207892 | AG29: =N29 * (1 - AB29) -> 8.2451244 | AK29: Year 20 | AL29: =MIN(AE29,J29) * G29 * 20 -> 3.3900681e+08 | AM29: =MIN(AG29,J29) * G29 * 20 -> 3.9253421e+08 | AN29: =$M$8 + Q29 * 20 -> 1.0791937e+08 | AO29: =$N$8 + T29 * 20 -> 1.6390854e+08 | AR29: =AE29 -> 7.1207892 | AS29: =AG29 -> 8.2451244 | AT29: =AL29-AN29 -> 2.3108745e+08 | AU29: =AM29-AO29 -> 2.2862566e+08

Sheet NPV - Allt.1
B13: Varity A | D13: Discount rate | E13: 0.06
A14: 1 | B14: ='Varity A - Carménère'!BB10 -> 3.1863967e+08 | P14: Histogram:
A15: 2 | B15: ='Varity A - Carménère'!BB11 -> 3.1698948e+08 | D15: NPV: | E15: =NPV(E13,B14:B33) -> 3.288014e+09
A16: 3 | B16: ='Varity A - Carménère'!BB12 -> 3.6832268e+08
A17: 4 | B17: ='Varity A - Carménère'!BB13 -> 2.2651084e+08
A18: 5 | B18: ='Varity A - Carménère'!BB14 -> 3.6487609e+08 | D18: 1000 Replications(scenarios) of NPV: | V18: Sample mean | W18: =I20 -> 3.0930249e+09
A19: 6 | B19: ='Varity A - Carménère'!BB15 -> 1.7516801e+08 | D19: Sample | E19: NPV | F19: NPV<1,7 Billion | G19: Probability of NPV<1,7 Billion | H19: Descriptive statisctics | J19: Diff: actual NPV and mean NPV | L19: Bin | M19: Frequency | V19: Standard Deviation | W19: =I24 -> 1.8124832e+08
A20: 7 | B20: ='Varity A - Carménère'!BB16 -> 1.9335784e+08 | C20: =COUNTIF(E20:E1019,"<1700000000")/1000 -> 0 | D20: 1 | E20: =E15 -> 3.288014e+09 | F20: =IF(E20<1700000000,1,0) -> 0 | G20: =SUM(F20:F1019)/1000 -> 0 | H20: Mean | I20: 3.0930249e+09 | J20: =E15-I20 -> 1.9498906e+08 | L20: 2.4304594e+09 | M20: 0 | V20: Sample size | W20: 1000
A21: 8 | B21: ='Varity A - Carménère'!BB17 -> 2.9592325e+08 | D21: 2 | E21: 3.3233212e+09 | F21: =IF(E21<1700000000,1,0) -> 0 | H21: Standard Error | I21: 5731575.3 | L21: 2.4683458e+09 | M21: 0 | V21: Confidence level | W21: 0.95
A22: 9 | B22: ='Varity A - Carménère'!BB18 -> 3.0512252e+08 | D22: 3 | E22: 3.2987266e+09 | F22: =IF(E22<1700000000,1,0) -> 0 | H22: Median | I22: 3.0948297e+09 | L22: 2.5062322e+09 | M22: 0
A23: 10 | B23: ='Varity A - Carménère'!BB19 -> 2.3232579e+08 | D23: 4 | E23: 3.136445e+09 | F23: =IF(E23<1700000000,1,0) -> 0 | H23: Mode | I23: #N/A | L23: 2.5441186e+09 | M23: 0 | V23: Margin of error | W23: =_xlfn.CONFIDENCE.NORM(1-W21,W19,W20) -> 11233681
A24: 11 | B24: ='Varity A - Carménère'!BB20 -> 3.4002943e+08 | D24: 5 | E24: 3.2838756e+09 | F24: =IF(E24<1700000000,1,0) -> 0 | H24: Standard Deviation | I24: 1.8124832e+08 | L24: 2.582005e+09 | M24: 1 | V24: Lower estimat | W24: =W18-W23 -> 3.0817912e+09
A25: 12 | B25: ='Varity A - Carménère'!BB21 -> 1.913875e+08 | D25: 6 | E25: 3.1823948e+09 | F25: =IF(E25<1700000000,1,0) -> 0 | H25: Sample Variance | I25: 3.2850955e+16 | L25: 2.6198914e+09 | M25: 3 | V25: Upper estimat | W25: =W18+W23 -> 3.1042586e+09
A26: 13 | B26: ='Varity A - Carménère'!BB22 -> 2.0788888e+08 | D26: 7 | E26: 3.3625443e+09 | F26: =IF(E26<1700000000,1,0) -> 0 | H26: Kurtosis | I26: -0.12840417 | L26: 2.6577778e+09 | M26: 4 | V26: 95% CL range | W26: =W25-W24 -> 22467362
A27: 14 | B27: ='Varity A - Carménère'!BB23 -> 3.7776926e+08 | D27: 8 | E27: 3.2092445e+09 | F27: =IF(E27<1700000000,1,0) -> 0 | H27: Skewness | I27: 0.054353264 | L27: 2.6956642e+09 | M27: 10
A28: 15 | B28: ='Varity A - Carménère'!BB24 -> 3.7270673e+08 | D28: 9 | E28: 3.2293547e+09 | F28: =IF(E28<1700000000,1,0) -> 0 | H28: Range | I28: 1.1529267e+09 | L28: 2.7335506e+09 | M28: 9
A29: 16 | B29: ='Varity A - Carménère'!BB25 -> 3.0944985e+08 | D29: 10 | E29: 3.3994558e+09 | F29: =IF(E29<1700000000,1,0) -> 0 | H29: Minimum | I29: 2.5214565e+09 | L29: 2.771437e+09 | M29: 16
A30: 17 | B30: ='Varity A - Carménère'!BB26 -> 2.9989037e+08 | D30: 11 | E30: 2.9777707e+09 | F30: =IF(E30<1700000000,1,0) -> 0 | H30: Maximum | I30: 3.6743832e+09 | L30: 2.8093234e+09 | M30: 12
A31: 18 | B31: ='Varity A - Carménère'!BB27 -> 2.1741285e+08 | D31: 12 | E31: 3.139405e+09 | F31: =IF(E31<1700000000,1,0) -> 0 | H31: Sum | I31: 3.0930249e+12 | L31: 2.8472098e+09 | M31: 19
A32: 19 | B32: ='Varity A - Carménère'!BB28 -> 3.8701978e+08 | D32: 13 | E32: 2.9796352e+09 | F32: =IF(E32<1700000000,1,0) -> 0 | H32: Count | I32: 1000 | L32: 2.8850963e+09 | M32: 30
A33: 20 | B33: ='Varity A - Carménère'!BB29 -> 2.0626016e+08 | D33: 14 | E33: 3.1756124e+09 | F33: =IF(E33<1700000000,1,0) -> 0 | L33: 2.9229827e+09 | M33: 33
D34: 15 | E34: 3.1219623e+09 | F34: =IF(E34<1700000000,1,0) -> 0 | L34: 2.9608691e+09 | M34: 68
D35: 16 | E35: 2.8628673e+09 | F35: =IF(E35<1700000000,1,0) -> 0 | L35: 2.9987555e+09 | M35: 70
D36: 17 | E36: 2.8588031e+09 | F36: =IF(E36<1700000000,1,0) -> 0 | L36: 3.0366419e+09 | M36: 73
D37: 18 | E37: 3.2393511e+09 | F37: =IF(E37<1700000000,1,0) -> 0 | L37: 3.0745283e+09 | M37: 82
D38: 19 | E38: 3.0676597e+09 | F38: =IF(E38<1700000000,1,0) -> 0 | L38: 3.1124147e+09 | M38: 84
D39: 20 | E39: 2.8262286e+09 | F39: =IF(E39<1700000000,1,0) -> 0 | L39: 3.1503011e+09 | M39: 94
D40: 21 | E40: 3.3473604e+09 | F40: =IF(E40<1700000000,1,0) -> 0 | L40: 3.1881875e+09 | M40: 97
D41: 22 | E41: 3.1813573e+09 | F41: =IF(E41<1700000000,1,0) -> 0 | L41: 3.2260739e+09 | M41: 57
D42: 23 | E42: 3.1998409e+09 | F42: =IF(E42<1700000000,1,0) -> 0 | L42: 3.2639603e+09 | M42: 51
D43: 24 | E43: 3.2396217e+09 | F43: =IF(E43<1700000000,1,0) -> 0 | L43: 3.3018467e+09 | M43: 55
D44: 25 | E44: 2.9342627e+09 | F44: =IF(E44<1700000000,1,0) -> 0 | L44: 3.3397331e+09 | M44: 44
D45: 26 | E45: 3.0238397e+09 | F45: =IF(E45<1700000000,1,0) -> 0 | L45: 3.3776195e+09 | M45: 27
... D50: 31 | E50: 3.3150247e+09 | F50: =IF(E50<1700000000,1,0) -> 0 | L50: 3.5670515e+09 | M50: 5
D51: 32 | E51: 3.1411675e+09 | F51: =IF(E51<1700000000,1,0) -> 0 | L51: More | M51: 9
D52: 33 | E52: 3.0298001e+09 | F52: =IF(E52<1700000000,1,0) -> 0
D53: 34 | E53: 3.1850966e+09 | F53: =IF(E53<1700000000,1,0) -> 0
D54: 35 | E54: 2.7391275e+09 | F54: =IF(E54<1700000000,1,0) -> 0
D55: 36 | E55: 2.8388465e+09 | F55: =IF(E55<1700000000,1,0) -> 0
D56: 37 | E56: 3.1641596e+09 | F56: =IF(E56<1700000000,1,0) -> 0
D57: 38 | E57: 2.9839466e+09 | F57: =IF(E57<1700000000,1,0) -> 0
D58: 39 | E58: 3.1497977e+09 | F58: =IF(E58<1700000000,1,0) -> 0
D59: 40 | E59: 3.0507669e+09 | F59: =IF(E59<1700000000,1,0) -> 0
D60: 41 | E60: 2.8392259e+09 | F60: =IF(E60<1700000000,1,0) -> 0
D61: 42 | E61: 3.1298684e+09 | F61: =IF(E61<1700000000,1,0) -> 0
D62: 43 | E62: 3.1056656e+09 | F62: =IF(E62<1700000000,1,0) -> 0
D63: 44 | E63: 3.1962923e+09 | F63: =IF(E63<1700000000,1,0) -> 0
... D1019: 1000 | E1019: 3.0845637e+09 | F1019: =IF(E1019<1700000000,1,0) -> 0

Sheet NPV - Allt.2
Q12: Histogram:
C14: Varity C | E14: Discount rate | F14: 0.06
B15: 1 | C15: ='Varity C - Syrah'!AU10 -> 2.0918437e+08
B16: 2 | C16: ='Varity C - Syrah'!AU11 -> 3.8893587e+08
B17: 3 | C17: ='Varity C - Syrah'!AU12 -> 1.4676358e+08 | E17: NPV: | F17: =NPV(F14,C15:C34) -> 2.860337e+09
B18: 4 | C18: ='Varity C - Syrah'!AU13 -> 2.6290423e+08
B19: 5 | C19: ='Varity C - Syrah'!AU14 -> 4.8800023e+08 | E19: 1000 replications of NPV:
B20: 6 | C20: ='Varity C - Syrah'!AU15 -> 3.0624238e+08 | E20: Sample | F20: NPV | G20: NPV<1,7 Billion | H20: Probability of NPV<1,7 Billion | J20: Descriptive Statistics | L20: Diff | N20: Bin | O20: Frequency | W20: Sample mean | X20: =K21 -> 3.1191679e+09
B21: 7 | C21: ='Varity C - Syrah'!AU16 -> 1.5900078e+08 | E21: 1 | F21: =F17 -> 2.860337e+09 | G21: =IF(F21<1700000000,1,0) -> 0 | H21: =SUM(G21:G1020)/1000 -> 0 | J21: Mean | K21: 3.1191679e+09 | L21: =F17-K21 -> -2.5883086e+08 | N21: 2.4974714e+09 | O21: 1 | W21: Standard Deviation | X21: =K25 -> 2.2339947e+08
B22: 8 | C22: ='Varity C - Syrah'!AU17 -> 3.4881637e+08 | E22: 2 | F22: 2.986731e+09 | G22: =IF(F22<1700000000,1,0) -> 0 | J22: Standard Error | K22: 7064511.7 | N22: 2.539368e+09 | O22: 2 | W22: Sample size | X22: 1000
B23: 9 | C23: ='Varity C - Syrah'!AU18 -> 90235929 | E23: 3 | F23: 3.0914902e+09 | G23: =IF(F23<1700000000,1,0) -> 0 | J23: Median | K23: 3.1169302e+09 | N23: 2.5812646e+09 | O23: 2 | W23: Confidence level | X23: 0.95
B24: 10 | C24: ='Varity C - Syrah'!AU19 -> 2.5005567e+08 | E24: 4 | F24: 2.9086267e+09 | G24: =IF(F24<1700000000,1,0) -> 0 | J24: Mode | K24: #N/A | N24: 2.6231611e+09 | O24: 4
B25: 11 | C25: ='Varity C - Syrah'!AU20 -> 1.7621157e+08 | E25: 5 | F25: 3.2777604e+09 | G25: =IF(F25<1700000000,1,0) -> 0 | J25: Standard Deviation | K25: 2.2339947e+08 | N25: 2.6650577e+09 | O25: 4 | W25: Margin of error | X25: =_xlfn.CONFIDENCE.NORM(1-X23,X21,X22) -> 13846188
B26: 12 | C26: ='Varity C - Syrah'!AU21 -> 3.0578529e+08 | E26: 6 | F26: 3.1170535e+09 | G26: =IF(F26<1700000000,1,0) -> 0 | J26: Sample Variance | K26: 4.9907325e+16 | N26: 2.7069543e+09 | O26: 11 | W26: Lower estimat | X26: =X20-X25 -> 3.1053217e+09
B27: 13 | C27: ='Varity C - Syrah'!AU22 -> 2.0926427e+08 | E27: 7 | F27: 3.0349582e+09 | G27: =IF(F27<1700000000,1,0) -> 0 | J27: Kurtosis | K27: 0.11515245 | N27: 2.7488509e+09 | O27: 18 | W27: Upper estimat | X27: =X20+X25 -> 3.1330141e+09
B28: 14 | C28: ='Varity C - Syrah'!AU23 -> 1.9611489e+08 | E28: 8 | F28: 3.0798994e+09 | G28: =IF(F28<1700000000,1,0) -> 0 | J28: Skewness | K28: -0.0070525836 | N28: 2.7907475e+09 | O28: 27 | W28: 95% CL range | X28: =X27-X26 -> 27692377
B29: 15 | C29: ='Varity C - Syrah'!AU24 -> 2.4548874e+08 | E29: 9 | F29: 3.0980298e+09 | G29: =IF(F29<1700000000,1,0) -> 0 | J29: Range | K29: 1.5636699e+09 | N29: 2.832644e+09 | O29: 26
B30: 16 | C30: ='Varity C - Syrah'!AU25 -> 2.6171415e+08 | E30: 10 | F30: 3.0484063e+09 | G30: =IF(F30<1700000000,1,0) -> 0 | J30: Minimum | K30: 2.2263695e+09 | N30: 2.8745406e+09 | O30: 36
B31: 17 | C31: ='Varity C - Syrah'!AU26 -> 1.3045884e+08 | E31: 11 | F31: 3.1235907e+09 | G31: =IF(F31<1700000000,1,0) -> 0 | J31: Maximum | K31: 3.7900394e+09 | N31: 2.9164372e+09 | O31: 59
B32: 18 | C32: ='Varity C - Syrah'!AU27 -> 1.5459899e+08 | E32: 12 | F32: 2.7558673e+09 | G32: =IF(F32<1700000000,1,0) -> 0 | J32: Sum | K32: 3.1191679e+12 | N32: 2.9583338e+09 | O32: 55
B33: 19 | C33: ='Varity C - Syrah'!AU28 -> 2.3655667e+08 | E33: 13 | F33: 2.7626328e+09 | G33: =IF(F33<1700000000,1,0) -> 0 | J33: Count | K33: 1000 | N33: 3.0002304e+09 | O33: 57
B34: 20 | C34: ='Varity C - Syrah'!AU29 -> 2.2862566e+08 | E34: 14 | F34: 3.1495122e+09 | G34: =IF(F34<1700000000,1,0) -> 0 | N34: 3.0421269e+09 | O34: 60
E35: 15 | F35: 2.9996915e+09 | G35: =IF(F35<1700000000,1,0) -> 0 | N35: 3.0840235e+09 | O35: 82
E36: 16 | F36: 3.1551814e+09 | G36: =IF(F36<1700000000,1,0) -> 0 | N36: 3.1259201e+09 | O36: 72
E37: 17 | F37: 3.1520736e+09 | G37: =IF(F37<1700000000,1,0) -> 0 | N37: 3.1678167e+09 | O37: 74
E38: 18 | F38: 2.9429472e+09 | G38: =IF(F38<1700000000,1,0) -> 0 | N38: 3.2097133e+09 | O38: 76
E39: 19 | F39: 3.1508519e+09 | G39: =IF(F39<1700000000,1,0) -> 0 | N39: 3.2516098e+09 | O39: 63
E40: 20 | F40: 3.216461e+09 | G40: =IF(F40<1700000000,1,0) -> 0 | N40: 3.2935064e+09 | O40: 66
E41: 21 | F41: 3.2277787e+09 | G41: =IF(F41<1700000000,1,0) -> 0 | N41: 3.335403e+09 | O41: 60
E42: 22 | F42: 3.056985e+09 | G42: =IF(F42<1700000000,1,0) -> 0 | N42: 3.3772996e+09 | O42: 41
E43: 23 | F43: 3.0214821e+09 | G43: =IF(F43<1700000000,1,0) -> 0 | N43: 3.4191962e+09 | O43: 27
E44: 24 | F44: 3.1330665e+09 | G44: =IF(F44<1700000000,1,0) -> 0 | N44: 3.4610928e+09 | O44: 25
E45: 25 | F45: 2.8971499e+09 | G45: =IF(F45<1700000000,1,0) -> 0 | N45: 3.5029893e+09 | O45: 16
E46: 26 | F46: 2.9281171e+09 | G46: =IF(F46<1700000000,1,0) -> 0 | N46: 3.5448859e+09 | O46: 6
... E51: 31 | F51: 3.4494498e+09 | G51: =IF(F51<1700000000,1,0) -> 0 | N51: 3.7543688e+09 | O51: 0
E52: 32 | F52: 3.3008416e+09 | G52: =IF(F52<1700000000,1,0) -> 0 | N52: More | O52: 2
E53: 33 | F53: 3.0174644e+09 | G53: =IF(F53<1700000000,1,0) -> 0
E54: 34 | F54: 3.3445692e+09 | G54: =IF(F54<1700000000,1,0) -> 0
E55: 35 | F55: 3.292769e+09 | G55: =IF(F55<1700000000,1,0) -> 0
E56: 36 | F56: 2.9773497e+09 | G56: =IF(F56<1700000000,1,0) -> 0
E57: 37 | F57: 3.5163836e+09 | G57: =IF(F57<1700000000,1,0) -> 0
E58: 38 | F58: 3.5075121e+09 | G58: =IF(F58<1700000000,1,0) -> 0
E59: 39 | F59: 2.9197765e+09 | G59: =IF(F59<1700000000,1,0) -> 0
E60: 40 | F60: 3.2063533e+09 | G60: =IF(F60<1700000000,1,0) -> 0
E61: 41 | F61: 3.0978047e+09 | G61: =IF(F61<1700000000,1,0) -> 0
E62: 42 | F62: 3.0976223e+09 | G62: =IF(F62<1700000000,1,0) -> 0
E63: 43 | F63: 3.5172628e+09 | G63: =IF(F63<1700000000,1,0) -> 0
E64: 44 | F64: 2.8232988e+09 | G64: =IF(F64<1700000000,1,0) -> 0
... E1020: 1000 | F1020: 3.5218985e+09 | G1020: =IF(F1020<1700000000,1,0) -> 0

Sheet NPV - Allt.3
I6: Discount rate | J6: 0.06
I8: NPV | J8: =NPV(J6,H15:H34) -> 3.006738e+09 | V8: Histogram:
J10: 1000 replications for NPV:
J11: Sample | K11: NPV | L11: NPV>1,7 Billion | M11: Probability of NPV < 1,7 Billion | O11: Descriptive Statistics Alt 3 | Q11: Diff: actual NPV and mean NPV | S11: Bin | T11: Frequency | AC11: Sample mean | AD11: =P13 -> 2.957658e+09
J12: 1 | K12: =J8 -> 3.006738e+09 | L12: =IF(K12<1700000000,1,0) -> 0 | M12: =SUM(L12:L1011)/1000 -> 0 | Q12: =J8-P13 -> 49079920 | S12: 2.5069138e+09 | T12: 0 | AC12: Standard Deviation | AD12: =P17 -> 1.3031724e+08
J13: 2 | K13: 2.8829922e+09 | L13: =IF(K13<1700000000,1,0) -> 0 | O13: Mean | P13: 2.957658e+09 | S13: 2.5360737e+09 | T13: 0 | AC13: Sample size | AD13: 1000
C14: Varity A | D14: Varity B | F14: Profit/2 Varity A | G14: Profit/2 Varity B | H14: SUM Profit A + Profit B | J14: 3 | K14: 2.8988654e+09 | L14: =IF(K14<1700000000,1,0) -> 0 | O14: Standard Error | P14: 4120993.1 | S14: 2.5652337e+09 | T14: 2 | AC14: Confidence level | AD14: 0.95
B15: 1 | C15: ='Varity A - Carménère'!BB10 -> 3.1863967e+08 | D15: ='Varity B - Cabarnet Savignon'!AV12 -> 3.0136865e+08 | F15: =C15/2 -> 1.5931984e+08 | G15: =D15/2 -> 1.5068433e+08 | H15: =F15+G15 -> 3.1000416e+08 | J15: 4 | K15: 2.9394166e+09 | L15: =IF(K15<1700000000,1,0) -> 0 | O15: Median | P15: 2.9551091e+09 | S15: 2.5943936e+09 | T15: 2
B16: 2 | C16: ='Varity A - Carménère'!BB11 -> 3.1698948e+08 | D16: ='Varity B - Cabarnet Savignon'!AV13 -> 3.0435726e+08 | F16: =C16/2 -> 1.5849474e+08 | G16: =D16/2 -> 1.5217863e+08 | H16: =F16+G16 -> 3.1067337e+08 | J16: 5 | K16: 2.9785378e+09 | L16: =IF(K16<1700000000,1,0) -> 0 | O16: Mode | P16: #N/A | S16: 2.6235536e+09 | T16: 0 | AC16: Margin of error | AD16: =_xlfn.CONFIDENCE.NORM(1-AD14,AD12,AD13) -> 8076998
B17: 3 | C17: ='Varity A - Carménère'!BB12 -> 3.6832268e+08 | D17: ='Varity B - Cabarnet Savignon'!AV14 -> 4.1725232e+08 | F17: =C17/2 -> 1.8416134e+08 | G17: =D17/2 -> 2.0862616e+08 | H17: =F17+G17 -> 3.927875e+08 | J17: 6 | K17: 2.9047032e+09 | L17: =IF(K17<1700000000,1,0) -> 0 | O17: Standard Deviation | P17: 1.3031724e+08 | S17: 2.6527136e+09 | T17: 7 | AC17: Lower estimat | AD17: =AD11-AD16 -> 2.9495811e+09
B18: 4 | C18: ='Varity A - Carménère'!BB13 -> 2.2651084e+08 | D18: ='Varity B - Cabarnet Savignon'!AV15 -> 2.0669482e+08 | F18: =C18/2 -> 1.1325542e+08 | G18: =D18/2 -> 1.0334741e+08 | H18: =F18+G18 -> 2.1660283e+08 | J18: 7 | K18: 2.9622196e+09 | L18: =IF(K18<1700000000,1,0) -> 0 | O18: Sample Variance | P18: 1.6982584e+16 | S18: 2.6818735e+09 | T18: 12 | AC18: Upper estimat | AD18: =AD11+AD16 -> 2.965735e+09
B19: 5 | C19: ='Varity A - Carménère'!BB14 -> 3.6487609e+08 | D19: ='Varity B - Cabarnet Savignon'!AV16 -> 2.1370399e+08 | F19: =C19/2 -> 1.8243804e+08 | G19: =D19/2 -> 1.0685199e+08 | H19: =F19+G19 -> 2.8929004e+08 | J19: 8 | K19: 3.0048693e+09 | L19: =IF(K19<1700000000,1,0) -> 0 | O19: Kurtosis | P19: 0.047295803 | S19: 2.7110335e+09 | T19: 10 | AC19: 95% CL range | AD19: =AD18-AD17 -> 16153996
B20: 6 | C20: ='Varity A - Carménère'!BB15 -> 1.7516801e+08 | D20: ='Varity B - Cabarnet Savignon'!AV17 -> 2.2292459e+08 | F20: =C20/2 -> 87584007 | G20: =D20/2 -> 1.1146229e+08 | H20: =F20+G20 -> 1.990463e+08 | J20: 9 | K20: 3.0024534e+09 | L20: =IF(K20<1700000000,1,0) -> 0 | O20: Skewness | P20: 0.017655722 | S20: 2.7401934e+09 | T20: 16
B21: 7 | C21: ='Varity A - Carménère'!BB16 -> 1.9335784e+08 | D21: ='Varity B - Cabarnet Savignon'!AV18 -> 2.4930659e+08 | F21: =C21/2 -> 96678919 | G21: =D21/2 -> 1.2465329e+08 | H21: =F21+G21 -> 2.2133221e+08 | J21: 10 | K21: 2.8616118e+09 | L21: =IF(K21<1700000000,1,0) -> 0 | O21: Range | P21: 8.1335579e+08 | S21: 2.7693534e+09 | T21: 28 | AD21: The lower the range the better and more accurate is our model.
B22: 8 | C22: ='Varity A - Carménère'!BB17 -> 2.9592325e+08 | D22: ='Varity B - Cabarnet Savignon'!AV19 -> 2.3755075e+08 | F22: =C22/2 -> 1.4796163e+08 | G22: =D22/2 -> 1.1877537e+08 | H22: =F22+G22 -> 2.66737e+08 | J22: 11 | K22: 2.8824551e+09 | L22: =IF(K22<1700000000,1,0) -> 0 | O22: Minimum | P22: 2.5593149e+09 | S22: 2.7985133e+09 | T22: 40
B23: 9 | C23: ='Varity A - Carménère'!BB18 -> 3.0512252e+08 | D23: ='Varity B - Cabarnet Savignon'!AV20 -> 1.7318905e+08 | F23: =C23/2 -> 1.5256126e+08 | G23: =D23/2 -> 86594525 | H23: =F23+G23 -> 2.3915579e+08 | J23: 12 | K23: 3.0236579e+09 | L23: =IF(K23<1700000000,1,0) -> 0 | O23: Maximum | P23: 3.3726707e+09 | S23: 2.8276733e+09 | T23: 52
B24: 10 | C24: ='Varity A - Carménère'!BB19 -> 2.3232579e+08 | D24: ='Varity B - Cabarnet Savignon'!AV21 -> 1.0254625e+08 | F24: =C24/2 -> 1.1616289e+08 | G24: =D24/2 -> 51273124 | H24: =F24+G24 -> 1.6743602e+08 | J24: 13 | K24: 3.1497721e+09 | L24: =IF(K24<1700000000,1,0) -> 0 | O24: Sum | P24: 2.957658e+12 | S24: 2.8568332e+09 | T24: 65
B25: 11 | C25: ='Varity A - Carménère'!BB20 -> 3.4002943e+08 | D25: ='Varity B - Cabarnet Savignon'!AV22 -> 1.7329948e+08 | F25: =C25/2 -> 1.7001471e+08 | G25: =D25/2 -> 86649740 | H25: =F25+G25 -> 2.5666445e+08 | J25: 14 | K25: 2.8907216e+09 | L25: =IF(K25<1700000000,1,0) -> 0 | O25: Count | P25: 1000 | S25: 2.8859932e+09 | T25: 76
B26: 12 | C26: ='Varity A - Carménère'!BB21 -> 1.913875e+08 | D26: ='Varity B - Cabarnet Savignon'!AV23 -> 2.8015441e+08 | F26: =C26/2 -> 95693750 | G26: =D26/2 -> 1.400772e+08 | H26: =F26+G26 -> 2.3577095e+08 | J26: 15 | K26: 2.9491605e+09 | L26: =IF(K26<1700000000,1,0) -> 0 | S26: 2.9151531e+09 | T26: 67
B27: 13 | C27: ='Varity A - Carménère'!BB22 -> 2.0788888e+08 | D27: ='Varity B - Cabarnet Savignon'!AV24 -> 2.8201257e+08 | F27: =C27/2 -> 1.0394444e+08 | G27: =D27/2 -> 1.4100628e+08 | H27: =F27+G27 -> 2.4495072e+08 | J27: 16 | K27: 2.7382854e+09 | L27: =IF(K27<1700000000,1,0) -> 0 | S27: 2.9443131e+09 | T27: 83
B28: 14 | C28: ='Varity A - Carménère'!BB23 -> 3.7776926e+08 | D28: ='Varity B - Cabarnet Savignon'!AV25 -> 1.2268952e+08 | F28: =C28/2 -> 1.8888463e+08 | G28: =D28/2 -> 61344762 | H28: =F28+G28 -> 2.5022939e+08 | J28: 17 | K28: 3.0608542e+09 | L28: =IF(K28<1700000000,1,0) -> 0 | S28: 2.9734731e+09 | T28: 82
B29: 15 | C29: ='Varity A - Carménère'!BB24 -> 3.7270673e+08 | D29: ='Varity B - Cabarnet Savignon'!AV26 -> 2.6183277e+08 | F29: =C29/2 -> 1.8635336e+08 | G29: =D29/2 -> 1.3091638e+08 | H29: =F29+G29 -> 3.1726975e+08 | J29: 18 | K29: 2.8276259e+09 | L29: =IF(K29<1700000000,1,0) -> 0 | S29: 3.002633e+09 | T29: 95
B30: 16 | C30: ='Varity A - Carménère'!BB25 -> 3.0944985e+08 | D30: ='Varity B - Cabarnet Savignon'!AV27 -> 1.6652215e+08 | F30: =C30/2 -> 1.5472493e+08 | G30: =D30/2 -> 83261077 | H30: =F30+G30 -> 2.37986e+08 | J30: 19 | K30: 2.8337749e+09 | L30: =IF(K30<1700000000,1,0) -> 0 | S30: 3.031793e+09 | T30: 65
B31: 17 | C31: ='Varity A - Carménère'!BB26 -> 2.9989037e+08 | D31: ='Varity B - Cabarnet Savignon'!AV28 -> 55713529 | F31: =C31/2 -> 1.4994519e+08 | G31: =D31/2 -> 27856764 | H31: =F31+G31 -> 1.7780195e+08 | J31: 20 | K31: 2.7763435e+09 | L31: =IF(K31<1700000000,1,0) -> 0 | S31: 3.0609529e+09 | T31: 69
B32: 18 | C32: ='Varity A - Carménère'!BB27 -> 2.1741285e+08 | D32: ='Varity B - Cabarnet Savignon'!AV29 -> 3.0388698e+08 | F32: =C32/2 -> 1.0870642e+08 | G32: =D32/2 -> 1.5194349e+08 | H32: =F32+G32 -> 2.6064991e+08 | J32: 21 | K32: 2.7192826e+09 | L32: =IF(K32<1700000000,1,0) -> 0 | S32: 3.0901129e+09 | T32: 61
B33: 19 | C33: ='Varity A - Carménère'!BB28 -> 3.8701978e+08 | D33: ='Varity B - Cabarnet Savignon'!AV30 -> 1.2030501e+08 | F33: =C33/2 -> 1.9350989e+08 | G33: =D33/2 -> 60152503 | H33: =F33+G33 -> 2.536624e+08 | J33: 22 | K33: 2.7776223e+09 | L33: =IF(K33<1700000000,1,0) -> 0 | S33: 3.1192728e+09 | T33: 48
B34: 20 | C34: ='Varity A - Carménère'!BB29 -> 2.0626016e+08 | D34: ='Varity B - Cabarnet Savignon'!AV31 -> 3.4005905e+08 | F34: =C34/2 -> 1.0313008e+08 | G34: =D34/2 -> 1.7002953e+08 | H34: =F34+G34 -> 2.7315961e+08 | J34: 23 | K34: 2.9126411e+09 | L34: =IF(K34<1700000000,1,0) -> 0 | S34: 3.1484328e+09 | T34: 31
J35: 24 | K35: 2.8778929e+09 | L35: =IF(K35<1700000000,1,0) -> 0 | S35: 3.1775927e+09 | T35: 25
J36: 25 | K36: 2.784983e+09 | L36: =IF(K36<1700000000,1,0) -> 0 | S36: 3.2067527e+09 | T36: 17
J37: 26 | K37: 3.0410759e+09 | L37: =IF(K37<1700000000,1,0) -> 0 | S37: 3.2359126e+09 | T37: 12
J38: 27 | K38: 2.6565539e+09 | L38: =IF(K38<1700000000,1,0) -> 0 | S38: 3.2650726e+09 | T38: 14
J39: 28 | K39: 3.1376445e+09 | L39: =IF(K39<1700000000,1,0) -> 0 | S39: 3.2942326e+09 | T39: 6
J40: 29 | K40: 2.7707373e+09 | L40: =IF(K40<1700000000,1,0) -> 0 | S40: 3.3233925e+09 | T40: 6
J41: 30 | K41: 3.1491303e+09 | L41: =IF(K41<1700000000,1,0) -> 0 | S41: 3.3525525e+09 | T41: 4
J42: 31 | K42: 2.9924464e+09 | L42: =IF(K42<1700000000,1,0) -> 0 | S42: 3.3817124e+09 | T42: 3
J43: 32 | K43: 2.8943631e+09 | L43: =IF(K43<1700000000,1,0) -> 0 | S43: More | T43: 2
J44: 33 | K44: 3.0305783e+09 | L44: =IF(K44<1700000000,1,0) -> 0
J45: 34 | K45: 2.9268843e+09 | L45: =IF(K45<1700000000,1,0) -> 0
J46: 35 | K46: 2.9426031e+09 | L46: =IF(K46<1700000000,1,0) -> 0
J47: 36 | K47: 2.8411599e+09 | L47: =IF(K47<1700000000,1,0) -> 0
J48: 37 | K48: 2.8980297e+09 | L48: =IF(K48<1700000000,1,0) -> 0
J49: 38 | K49: 2.8655742e+09 | L49: =IF(K49<1700000000,1,0) -> 0
J50: 39 | K50: 2.7276466e+09 | L50: =IF(K50<1700000000,1,0) -> 0
J51: 40 | K51: 3.1765546e+09 | L51: =IF(K51<1700000000,1,0) -> 0
J52: 41 | K52: 3.0850251e+09 | L52: =IF(K52<1700000000,1,0) -> 0
J53: 42 | K53: 3.0117845e+09 | L53: =IF(K53<1700000000,1,0) -> 0
J54: 43 | K54: 3.0102226e+09 | L54: =IF(K54<1700000000,1,0) -> 0
J55: 44 | K55: 2.9494943e+09 | L55: =IF(K55<1700000000,1,0) -> 0
... J1011: 1000 | K1011: 2.6670951e+09 | L1011: =IF(K1011<1700000000,1,0) -> 0

Sheet NPV - Allt.4
I5: Discount rate | J5: 0.06
I7: NPV: | J7: =NPV(J5,G13:G32) -> 2.8120331e+09 | X7: Histogram:
I9: 1000 replications/simulations | N9: Descriptive Statistics | P9: Diff: actual NPV and mean NPV | Q9: Sample mean | R9: =O11 -> 2.9608142e+09
I10: sample | J10: NPV: | K10: NPV<1,7 Billion | L10: Probability of NPV lower then 1,7 Billion | Q10: Standard Deviation | R10: =O15 -> 1.6160535e+08 | U10: Bin | V10: Frequency
I11: 1 | J11: =J7 -> 2.8120331e+09 | K11: =IF(J11<1700000000,1,0) -> 0 | L11: =SUM(K11:K1010)/1000 -> 0 | N11: Mean | O11: 2.9608142e+09 | P11: =J7-O11 -> -1.4878111e+08 | Q11: Sample size | R11: 1000 | U11: 2.422784e+09 | V11: 0
C12: Varity B | D12: Varity C | E12: Profit/2 Varity B | F12: Profit/2 Varity C | G12: Sum varity B + varity C | I12: 2 | J12: 2.9662494e+09 | K12: =IF(J12<1700000000,1,0) -> 0 | N12: Standard Error | O12: 5110409.9 | Q12: Confidence level | R12: 0.95 | U12: 2.4558361e+09 | V12: 1
B13: 1 | C13: ='Varity B - Cabarnet Savignon'!AW12 -> 3.0146338e+08 | D13: ='Varity C - Syrah'!AU10 -> 2.0918437e+08 | E13: =C13/2 -> 1.5073169e+08 | F13: =D13/2 -> 1.0459218e+08 | G13: =E13+F13 -> 2.5532387e+08 | I13: 3 | J13: 2.8460202e+09 | K13: =IF(J13<1700000000,1,0) -> 0 | N13: Median | O13: 2.9607061e+09 | U13: 2.4888882e+09 | V13: 0
B14: 2 | C14: ='Varity B - Cabarnet Savignon'!AW13 -> 2.9979434e+08 | D14: ='Varity C - Syrah'!AU11 -> 3.8893587e+08 | E14: =C14/2 -> 1.4989717e+08 | F14: =D14/2 -> 1.9446794e+08 | G14: =E14+F14 -> 3.4436511e+08 | I14: 4 | J14: 2.9974538e+09 | K14: =IF(J14<1700000000,1,0) -> 0 | N14: Mode | O14: #N/A | Q14: Margin of error | R14: =_xlfn.CONFIDENCE.NORM(1-R12,R10,R11) -> 10016219 | U14: 2.5219403e+09 | V14: 0
B15: 3 | C15: ='Varity B - Cabarnet Savignon'!AW14 -> 4.462573e+08 | D15: ='Varity C - Syrah'!AU12 -> 1.4676358e+08 | E15: =C15/2 -> 2.2312865e+08 | F15: =D15/2 -> 73381789 | G15: =E15+F15 -> 2.9651044e+08 | I15: 5 | J15: 3.1391184e+09 | K15: =IF(J15<1700000000,1,0) -> 0 | N15: Standard Deviation | O15: 1.6160535e+08 | Q15: Lower estimat | R15: =R9-R14 -> 2.950798e+09 | U15: 2.5549924e+09 | V15: 4
B16: 4 | C16: ='Varity B - Cabarnet Savignon'!AW15 -> 2.0061502e+08 | D16: ='Varity C - Syrah'!AU13 -> 2.6290423e+08 | E16: =C16/2 -> 1.0030751e+08 | F16: =D16/2 -> 1.3145211e+08 | G16: =E16+F16 -> 2.3175962e+08 | I16: 6 | J16: 2.7239395e+09 | K16: =IF(J16<1700000000,1,0) -> 0 | N16: Sample Variance | O16: 2.611629e+16 | Q16: Upper estimat | R16: =R9+R14 -> 2.9708304e+09 | U16: 2.5880445e+09 | V16: 5
B17: 5 | C17: ='Varity B - Cabarnet Savignon'!AW16 -> 2.0704387e+08 | D17: ='Varity C - Syrah'!AU14 -> 4.8800023e+08 | E17: =C17/2 -> 1.0352194e+08 | F17: =D17/2 -> 2.4400011e+08 | G17: =E17+F17 -> 3.4752205e+08 | I17: 7 | J17: 2.9257089e+09 | K17: =IF(J17<1700000000,1,0) -> 0 | N17: Kurtosis | O17: -0.10752432 | Q17: 95% CL range | R17: =R16-R15 -> 20032439 | U17: 2.6210966e+09 | V17: 5
B18: 6 | C18: ='Varity B - Cabarnet Savignon'!AW17 -> 2.2519709e+08 | D18: ='Varity C - Syrah'!AU15 -> 3.0624238e+08 | E18: =C18/2 -> 1.1259855e+08 | F18: =D18/2 -> 1.5312119e+08 | G18: =E18+F18 -> 2.6571974e+08 | I18: 8 | J18: 2.8140781e+09 | K18: =IF(J18<1700000000,1,0) -> 0 | N18: Skewness | O18: 0.11203523 | U18: 2.6541487e+09 | V18: 7
B19: 7 | C19: ='Varity B - Cabarnet Savignon'!AW18 -> 2.3576285e+08 | D19: ='Varity C - Syrah'!AU16 -> 1.5900078e+08 | E19: =C19/2 -> 1.1788143e+08 | F19: =D19/2 -> 79500388 | G19: =E19+F19 -> 1.9738182e+08 | I19: 9 | J19: 2.7840023e+09 | K19: =IF(J19<1700000000,1,0) -> 0 | N19: Range | O19: 1.0465636e+09 | U19: 2.6872008e+09 | V19: 15
B20: 8 | C20: ='Varity B - Cabarnet Savignon'!AW19 -> 2.3431449e+08 | D20: ='Varity C - Syrah'!AU17 -> 3.4881637e+08 | E20: =C20/2 -> 1.1715724e+08 | F20: =D20/2 -> 1.7440818e+08 | G20: =E20+F20 -> 2.9156543e+08 | I20: 10 | J20: 2.9909955e+09 | K20: =IF(J20<1700000000,1,0) -> 0 | N20: Minimum | O20: 2.4204575e+09 | U20: 2.7202529e+09 | V20: 24
B21: 9 | C21: ='Varity B - Cabarnet Savignon'!AW20 -> 2.5482296e+08 | D21: ='Varity C - Syrah'!AU18 -> 90235929 | E21: =C21/2 -> 1.2741148e+08 | F21: =D21/2 -> 45117964 | G21: =E21+F21 -> 1.7252944e+08 | I21: 11 | J21: 2.9917104e+09 | K21: =IF(J21<1700000000,1,0) -> 0 | N21: Maximum | O21: 3.4670212e+09 | U21: 2.753305e+09 | V21: 39
B22: 10 | C22: ='Varity B - Cabarnet Savignon'!AW21 -> 83084123 | D22: ='Varity C - Syrah'!AU19 -> 2.5005567e+08 | E22: =C22/2 -> 41542061 | F22: =D22/2 -> 1.2502783e+08 | G22: =E22+F22 -> 1.6656989e+08 | I22: 12 | J22: 2.9605004e+09 | K22: =IF(J22<1700000000,1,0) -> 0 | N22: Sum | O22: 2.9608142e+12 | U22: 2.7863571e+09 | V22: 41
B23: 11 | C23: ='Varity B - Cabarnet Savignon'!AW22 -> 1.6125533e+08 | D23: ='Varity C - Syrah'!AU20 -> 1.7621157e+08 | E23: =C23/2 -> 80627664 | F23: =D23/2 -> 88105783 | G23: =E23+F23 -> 1.6873345e+08 | I23: 13 | J23: 3.0681766e+09 | K23: =IF(J23<1700000000,1,0) -> 0 | N23: Count | O23: 1000 | U23: 2.8194092e+09 | V23: 57
B24: 12 | C24: ='Varity B - Cabarnet Savignon'!AW23 -> 2.797708e+08 | D24: ='Varity C - Syrah'!AU21 -> 3.0578529e+08 | E24: =C24/2 -> 1.398854e+08 | F24: =D24/2 -> 1.5289265e+08 | G24: =E24+F24 -> 2.9277805e+08 | I24: 14 | J24: 2.9671135e+09 | K24: =IF(J24<1700000000,1,0) -> 0 | U24: 2.8524613e+09 | V24: 57
B25: 13 | C25: ='Varity B - Cabarnet Savignon'!AW24 -> 2.7792395e+08 | D25: ='Varity C - Syrah'!AU22 -> 2.0926427e+08 | E25: =C25/2 -> 1.3896198e+08 | F25: =D25/2 -> 1.0463213e+08 | G25: =E25+F25 -> 2.4359411e+08 | I25: 15 | J25: 2.8664448e+09 | K25: =IF(J25<1700000000,1,0) -> 0 | U25: 2.8855134e+09 | V25: 77
B26: 14 | C26: ='Varity B - Cabarnet Savignon'!AW25 -> 90595402 | D26: ='Varity C - Syrah'!AU23 -> 1.9611489e+08 | E26: =C26/2 -> 45297701 | F26: =D26/2 -> 98057444 | G26: =E26+F26 -> 1.4335515e+08 | I26: 16 | J26: 2.9857364e+09 | K26: =IF(J26<1700000000,1,0) -> 0 | U26: 2.9185655e+09 | V26: 70
B27: 15 | C27: ='Varity B - Cabarnet Savignon'!AW26 -> 2.5715488e+08 | D27: ='Varity C - Syrah'!AU24 -> 2.4548874e+08 | E27: =C27/2 -> 1.2857744e+08 | F27: =D27/2 -> 1.2274437e+08 | G27: =E27+F27 -> 2.5132181e+08 | I27: 17 | J27: 2.9763941e+09 | K27: =IF(J27<1700000000,1,0) -> 0 | U27: 2.9516176e+09 | V27: 90
B28: 16 | C28: ='Varity B - Cabarnet Savignon'!AW27 -> 1.5587636e+08 | D28: ='Varity C - Syrah'!AU25 -> 2.6171415e+08 | E28: =C28/2 -> 77938182 | F28: =D28/2 -> 1.3085708e+08 | G28: =E28+F28 -> 2.0879526e+08 | I28: 18 | J28: 3.167917e+09 | K28: =IF(J28<1700000000,1,0) -> 0 | U28: 2.9846697e+09 | V28: 95
B29: 17 | C29: ='Varity B - Cabarnet Savignon'!AW28 -> 1.4057519e+08 | D29: ='Varity C - Syrah'!AU26 -> 1.3045884e+08 | E29: =C29/2 -> 70287594 | F29: =D29/2 -> 65229421 | G29: =E29+F29 -> 1.3551701e+08 | I29: 19 | J29: 2.6970161e+09 | K29: =IF(J29<1700000000,1,0) -> 0 | U29: 3.0177218e+09 | V29: 74
B30: 18 | C30: ='Varity B - Cabarnet Savignon'!AW29 -> 3.1663054e+08 | D30: ='Varity C - Syrah'!AU27 -> 1.5459899e+08 | E30: =C30/2 -> 1.5831527e+08 | F30: =D30/2 -> 77299494 | G30: =E30+F30 -> 2.3561477e+08 | I30: 20 | J30: 2.9714283e+09 | K30: =IF(J30<1700000000,1,0) -> 0 | U30: 3.0507739e+09 | V30: 77
B31: 19 | C31: ='Varity B - Cabarnet Savignon'!AW30 -> 1.8260112e+08 | D31: ='Varity C - Syrah'!AU28 -> 2.3655667e+08 | E31: =C31/2 -> 91300560 | F31: =D31/2 -> 1.1827833e+08 | G31: =E31+F31 -> 2.0957889e+08 | I31: 21 | J31: 3.1261259e+09 | K31: =IF(J31<1700000000,1,0) -> 0 | U31: 3.083826e+09 | V31: 76
B32: 20 | C32: ='Varity B - Cabarnet Savignon'!AW31 -> 2.4988676e+08 | D32: ='Varity C - Syrah'!AU29 -> 2.2862566e+08 | E32: =C32/2 -> 1.2494338e+08 | F32: =D32/2 -> 1.1431283e+08 | G32: =E32+F32 -> 2.3925621e+08 | I32: 22 | J32: 2.8653377e+09 | K32: =IF(J32<1700000000,1,0) -> 0 | U32: 3.1168781e+09 | V32: 51
I33: 23 | J33: 3.0122845e+09 | K33: =IF(J33<1700000000,1,0) -> 0 | U33: 3.1499302e+09 | V33: 30
I34: 24 | J34: 2.8951338e+09 | K34: =IF(J34<1700000000,1,0) -> 0 | U34: 3.1829823e+09 | V34: 33
I35: 25 | J35: 2.8541618e+09 | K35: =IF(J35<1700000000,1,0) -> 0 | U35: 3.2160344e+09 | V35: 25
I36: 26 | J36: 3.0410294e+09 | K36: =IF(J36<1700000000,1,0) -> 0 | U36: 3.2490865e+09 | V36: 16
I37: 27 | J37: 2.6434925e+09 | K37: =IF(J37<1700000000,1,0) -> 0 | U37: 3.2821386e+09 | V37: 9
I38: 28 | J38: 3.1367718e+09 | K38: =IF(J38<1700000000,1,0) -> 0 | U38: 3.3151907e+09 | V38: 9
I39: 29 | J39: 3.0362897e+09 | K39: =IF(J39<1700000000,1,0) -> 0 | U39: 3.3482428e+09 | V39: 4
I40: 30 | J40: 2.9720484e+09 | K40: =IF(J40<1700000000,1,0) -> 0 | U40: 3.3812949e+09 | V40: 5
I41: 31 | J41: 2.8697281e+09 | K41: =IF(J41<1700000000,1,0) -> 0 | U41: 3.414347e+09 | V41: 2
I42: 32 | J42: 3.0353607e+09 | K42: =IF(J42<1700000000,1,0) -> 0 | U42: More | V42: 2
I43: 33 | J43: 2.7842086e+09 | K43: =IF(J43<1700000000,1,0) -> 0
I44: 34 | J44: 2.8321687e+09 | K44: =IF(J44<1700000000,1,0) -> 0
I45: 35 | J45: 2.8507247e+09 | K45: =IF(J45<1700000000,1,0) -> 0
I46: 36 | J46: 2.9550227e+09 | K46: =IF(J46<1700000000,1,0) -> 0
I47: 37 | J47: 2.9164968e+09 | K47: =IF(J47<1700000000,1,0) -> 0
I48: 38 | J48: 3.0359525e+09 | K48: =IF(J48<1700000000,1,0) -> 0
I49: 39 | J49: 2.9209634e+09 | K49: =IF(J49<1700000000,1,0) -> 0
I50: 40 | J50: 3.0529082e+09 | K50: =IF(J50<1700000000,1,0) -> 0
I51: 41 | J51: 2.9710537e+09 | K51: =IF(J51<1700000000,1,0) -> 0
I52: 42 | J52: 2.7125138e+09 | K52: =IF(J52<1700000000,1,0) -> 0
I53: 43 | J53: 3.1379903e+09 | K53: =IF(J53<1700000000,1,0) -> 0
I54: 44 | J54: 2.8687271e+09 | K54: =IF(J54<1700000000,1,0) -> 0
... I1010: 1000 | J1010: 2.9852983e+09 | K1010: =IF(J1010<1700000000,1,0) -> 0

Sheet NPV - Allt5.
H4: Discount rate | I4: 0.06
H6: NPV: | I6: =NPV(I4,F12:F31) -> 3.1090558e+09
H8: 1000 replications/simulations | J8: NPV<1,7 Billion | K8: Probability of NPV lower then 1,7 Billion
H9: Sample | I9: NPV: | K9: =SUM(J10:J1009)/1000 -> 0
H10: 1 | I10: =I6 -> 3.1090558e+09 | J10: =IF(I10<1700000000,1,0) -> 0
B11: Varity A | C11: Varity C | D11: Profit/2 Varity A | E11: Profit/2 Varity C | F11: Total Profit Varity A + Varity C | H11: 2 | I11: 3.0465646e+09 | J11: =IF(I11<1700000000,1,0) -> 0 | L11: Descriptive statistics Alt 5 | N11: Diff: actual NPV and mean NPV | O11: Average CLP | P11: Frequency | R11: Histogram: | Z11: Sample mean | AA11: =M13 -> 3.1435108e+09
A12: 1 | B12: ='Varity A - Carménère'!BC10 -> 3.312799e+08 | C12: ='Varity C - Syrah'!AU10 -> 2.0918437e+08 | D12: =B12/2 -> 1.6563995e+08 | E12: =C12/2 -> 1.0459218e+08 | F12: =D12+E12 -> 2.7023213e+08 | H12: 3 | I12: 3.0899081e+09 | J12: =IF(I12<1700000000,1,0) -> 0 | N12: =I6-M13 -> -34455012 | O12: 2.6812128e+09 | P12: 2 | Z12: Standard Deviation | AA12: =M17 -> 1.4957282e+08
A13: 2 | B13: ='Varity A - Carménère'!BC11 -> 3.3384194e+08 | C13: ='Varity C - Syrah'!AU11 -> 3.8893587e+08 | D13: =B13/2 -> 1.6692097e+08 | E13: =C13/2 -> 1.9446794e+08 | F13: =D13+E13 -> 3.6138891e+08 | H13: 4 | I13: 3.2812383e+09 | J13: =IF(I13<1700000000,1,0) -> 0 | L13: Mean | M13: 3.1435108e+09 | O13: 2.7105247e+09 | P13: 2 | Z13: Sample size | AA13: 1000
A14: 3 | B14: ='Varity A - Carménère'!BC12 -> 3.8605126e+08 | C14: ='Varity C - Syrah'!AU12 -> 1.4676358e+08 | D14: =B14/2 -> 1.9302563e+08 | E14: =C14/2 -> 73381789 | F14: =D14+E14 -> 2.6640742e+08 | H14: 5 | I14: 3.0303068e+09 | J14: =IF(I14<1700000000,1,0) -> 0 | L14: Standard Error | M14: 4729907.7 | O14: 2.7398365e+09 | P14: 1 | Z14: Confidence level | AA14: 0.95
A15: 4 | B15: ='Varity A - Carménère'!BC13 -> 2.2775782e+08 | C15: ='Varity C - Syrah'!AU13 -> 2.6290423e+08 | D15: =B15/2 -> 1.1387891e+08 | E15: =C15/2 -> 1.3145211e+08 | F15: =D15+E15 -> 2.4533102e+08 | H15: 6 | I15: 3.2332341e+09 | J15: =IF(I15<1700000000,1,0) -> 0 | L15: Median | M15: 3.1418629e+09 | O15: 2.7691484e+09 | P15: 6
A16: 5 | B16: ='Varity A - Carménère'!BC14 -> 3.7720866e+08 | C16: ='Varity C - Syrah'!AU14 -> 4.8800023e+08 | D16: =B16/2 -> 1.8860433e+08 | E16: =C16/2 -> 2.4400011e+08 | F16: =D16+E16 -> 4.3260444e+08 | H16: 7 | I16: 3.3976827e+09 | J16: =IF(I16<1700000000,1,0) -> 0 | L16: Mode | M16: #N/A | O16: 2.7984602e+09 | P16: 7 | Z16: Margin of error | AA16: =_xlfn.CONFIDENCE.NORM(1-AA14,AA12,AA13) -> 9270448.8
A17: 6 | B17: ='Varity A - Carménère'!BC15 -> 1.6319788e+08 | C17: ='Varity C - Syrah'!AU15 -> 3.0624238e+08 | D17: =B17/2 -> 81598940 | E17: =C17/2 -> 1.5312119e+08 | F17: =D17+E17 -> 2.3472013e+08 | H17: 8 | I17: 3.4054087e+09 | J17: =IF(I17<1700000000,1,0) -> 0 | L17: Standard Deviation | M17: 1.4957282e+08 | O17: 2.8277721e+09 | P17: 6 | Z17: Lower estimat | AA17: =AA11-AA16 -> 3.1342404e+09
A18: 7 | B18: ='Varity A - Carménère'!BC16 -> 1.8298137e+08 | C18: ='Varity C - Syrah'!AU16 -> 1.5900078e+08 | D18: =B18/2 -> 91490684 | E18: =C18/2 -> 79500388 | F18: =D18+E18 -> 1.7099107e+08 | H18: 9 | I18: 3.2003607e+09 | J18: =IF(I18<1700000000,1,0) -> 0 | L18: Sample Variance | M18: 2.2372027e+16 | O18: 2.8570839e+09 | P18: 15 | Z18: Upper estimat | AA18: =AA11+AA16 -> 3.1527813e+09
A19: 8 | B19: ='Varity A - Carménère'!BC17 -> 3.0673822e+08 | C19: ='Varity C - Syrah'!AU17 -> 3.4881637e+08 | D19: =B19/2 -> 1.5336911e+08 | E19: =C19/2 -> 1.7440818e+08 | F19: =D19+E19 -> 3.2777729e+08 | H19: 10 | I19: 2.8247951e+09 | J19: =IF(I19<1700000000,1,0) -> 0 | L19: Kurtosis | M19: 0.1064358 | O19: 2.8863958e+09 | P19: 18 | Z19: 95% CL range | AA19: =AA18-AA17 -> 18540898
A20: 9 | B20: ='Varity A - Carménère'!BC18 -> 3.1569094e+08 | C20: ='Varity C - Syrah'!AU18 -> 90235929 | D20: =B20/2 -> 1.5784547e+08 | E20: =C20/2 -> 45117964 | F20: =D20+E20 -> 2.0296343e+08 | H20: 11 | I20: 3.1579672e+09 | J20: =IF(I20<1700000000,1,0) -> 0 | L20: Skewness | M20: 0.0011080753 | O20: 2.9157077e+09 | P20: 31
A21: 10 | B21: ='Varity A - Carménère'!BC19 -> 2.2085751e+08 | C21: ='Varity C - Syrah'!AU19 -> 2.5005567e+08 | D21: =B21/2 -> 1.1042875e+08 | E21: =C21/2 -> 1.2502783e+08 | F21: =D21+E21 -> 2.3545659e+08 | H21: 12 | I21: 3.1534241e+09 | J21: =IF(I21<1700000000,1,0) -> 0 | L21: Range | M21: 1.0103401e+09 | O21: 2.9450195e+09 | P21: 25
A22: 11 | B22: ='Varity A - Carménère'!BC20 -> 3.4469245e+08 | C22: ='Varity C - Syrah'!AU20 -> 1.7621157e+08 | D22: =B22/2 -> 1.7234623e+08 | E22: =C22/2 -> 88105783 | F22: =D22+E22 -> 2.6045201e+08 | H22: 13 | I22: 3.3255485e+09 | J22: =IF(I22<1700000000,1,0) -> 0 | L22: Minimum | M22: 2.6249396e+09 | O22: 2.9743314e+09 | P22: 40
A23: 12 | B23: ='Varity A - Carménère'!BC21 -> 1.8804954e+08 | C23: ='Varity C - Syrah'!AU21 -> 3.0578529e+08 | D23: =B23/2 -> 94024769 | E23: =C23/2 -> 1.5289265e+08 | F23: =D23+E23 -> 2.4691742e+08 | H23: 14 | I23: 2.8162057e+09 | J23: =IF(I23<1700000000,1,0) -> 0 | L23: Maximum | M23: 3.6352797e+09 | O23: 3.0036432e+09 | P23: 41
A24: 13 | B24: ='Varity A - Carménère'!BC22 -> 2.0148478e+08 | C24: ='Varity C - Syrah'!AU22 -> 2.0926427e+08 | D24: =B24/2 -> 1.0074239e+08 | E24: =C24/2 -> 1.0463213e+08 | F24: =D24+E24 -> 2.0537453e+08 | H24: 15 | I24: 3.4053757e+09 | J24: =IF(I24<1700000000,1,0) -> 0 | L24: Sum | M24: 3.1435108e+12 | O24: 3.0329551e+09 | P24: 52
A25: 14 | B25: ='Varity A - Carménère'!BC23 -> 3.9776502e+08 | C25: ='Varity C - Syrah'!AU23 -> 1.9611489e+08 | D25: =B25/2 -> 1.9888251e+08 | E25: =C25/2 -> 98057444 | F25: =D25+E25 -> 2.9693995e+08 | H25: 16 | I25: 3.1217163e+09 | J25: =IF(I25<1700000000,1,0) -> 0 | L25: Count | M25: 1000 | O25: 3.0622669e+09 | P25: 79
A26: 15 | B26: ='Varity A - Carménère'!BC24 -> 3.9313899e+08 | C26: ='Varity C - Syrah'!AU24 -> 2.4548874e+08 | D26: =B26/2 -> 1.965695e+08 | E26: =C26/2 -> 1.2274437e+08 | F26: =D26+E26 -> 3.1931387e+08 | H26: 17 | I26: 3.0494884e+09 | J26: =IF(I26<1700000000,1,0) -> 0 | O26: 3.0915788e+09 | P26: 75
A27: 16 | B27: ='Varity A - Carménère'!BC25 -> 3.2248496e+08 | C27: ='Varity C - Syrah'!AU25 -> 2.6171415e+08 | D27: =B27/2 -> 1.6124248e+08 | E27: =C27/2 -> 1.3085708e+08 | F27: =D27+E27 -> 2.9209956e+08 | H27: 18 | I27: 3.1362146e+09 | J27: =IF(I27<1700000000,1,0) -> 0 | O27: 3.1208907e+09 | P27: 66
A28: 17 | B28: ='Varity A - Carménère'!BC26 -> 3.0795809e+08 | C28: ='Varity C - Syrah'!AU26 -> 1.3045884e+08 | D28: =B28/2 -> 1.5397904e+08 | E28: =C28/2 -> 65229421 | F28: =D28+E28 -> 2.1920847e+08 | H28: 19 | I28: 2.9518872e+09 | J28: =IF(I28<1700000000,1,0) -> 0 | O28: 3.1502025e+09 | P28: 86
A29: 18 | B29: ='Varity A - Carménère'!BC27 -> 2.1081535e+08 | C29: ='Varity C - Syrah'!AU27 -> 1.5459899e+08 | D29: =B29/2 -> 1.0540768e+08 | E29: =C29/2 -> 77299494 | F29: =D29+E29 -> 1.8270717e+08 | H29: 20 | I29: 3.4591156e+09 | J29: =IF(I29<1700000000,1,0) -> 0 | O29: 3.1795144e+09 | P29: 74
A30: 19 | B30: ='Varity A - Carménère'!BC28 -> 4.0875745e+08 | C30: ='Varity C - Syrah'!AU28 -> 2.3655667e+08 | D30: =B30/2 -> 2.0437873e+08 | E30: =C30/2 -> 1.1827833e+08 | F30: =D30+E30 -> 3.2265706e+08 | H30: 21 | I30: 2.8695668e+09 | J30: =IF(I30<1700000000,1,0) -> 0 | O30: 3.2088262e+09 | P30: 52
A31: 20 | B31: ='Varity A - Carménère'!BC29 -> 2.0076219e+08 | C31: ='Varity C - Syrah'!AU29 -> 2.2862566e+08 | D31: =B31/2 -> 1.0038109e+08 | E31: =C31/2 -> 1.1431283e+08 | F31: =D31+E31 -> 2.1469392e+08 | H31: 22 | I31: 3.1976622e+09 | J31: =IF(I31<1700000000,1,0) -> 0 | O31: 3.2381381e+09 | P31: 57
H32: 23 | I32: 3.3651686e+09 | J32: =IF(I32<1700000000,1,0) -> 0 | O32: 3.2674499e+09 | P32: 57
H33: 24 | I33: 3.1929867e+09 | J33: =IF(I33<1700000000,1,0) -> 0 | O33: 3.2967618e+09 | P33: 44
H34: 25 | I34: 3.1395417e+09 | J34: =IF(I34<1700000000,1,0) -> 0 | O34: 3.3260737e+09 | P34: 52
H35: 26 | I35: 3.1719067e+09 | J35: =IF(I35<1700000000,1,0) -> 0 | O35: 3.3553855e+09 | P35: 33
H36: 27 | I36: 3.1745106e+09 | J36: =IF(I36<1700000000,1,0) -> 0 | O36: 3.3846974e+09 | P36: 20
H37: 28 | I37: 3.0117816e+09 | J37: =IF(I37<1700000000,1,0) -> 0 | O37: 3.4140092e+09 | P37: 21
H38: 29 | I38: 2.9137705e+09 | J38: =IF(I38<1700000000,1,0) -> 0 | O38: 3.4433211e+09 | P38: 11
H39: 30 | I39: 3.1391411e+09 | J39: =IF(I39<1700000000,1,0) -> 0 | O39: 3.4726329e+09 | P39: 13
H40: 31 | I40: 3.2471668e+09 | J40: =IF(I40<1700000000,1,0) -> 0 | O40: 3.5019448e+09 | P40: 5
H41: 32 | I41: 2.8689585e+09 | J41: =IF(I41<1700000000,1,0) -> 0 | O41: 3.5312567e+09 | P41: 3
H42: 33 | I42: 3.1522881e+09 | J42: =IF(I42<1700000000,1,0) -> 0 | O42: 3.5605685e+09 | P42: 4
H43: 34 | I43: 2.9415773e+09 | J43: =IF(I43<1700000000,1,0) -> 0 | O43: More | P43: 2
H44: 35 | I44: 3.2446423e+09 | J44: =IF(I44<1700000000,1,0) -> 0
H45: 36 | I45: 3.2464952e+09 | J45: =IF(I45<1700000000,1,0) -> 0
H46: 37 | I46: 3.1488879e+09 | J46: =IF(I46<1700000000,1,0) -> 0
H47: 38 | I47: 3.4046461e+09 | J47: =IF(I47<1700000000,1,0) -> 0
H48: 39 | I48: 3.0956583e+09 | J48: =IF(I48<1700000000,1,0) -> 0
H49: 40 | I49: 3.2181439e+09 | J49: =IF(I49<1700000000,1,0) -> 0
H50: 41 | I50: 3.0747353e+09 | J50: =IF(I50<1700000000,1,0) -> 0
H51: 42 | I51: 2.9726043e+09 | J51: =IF(I51<1700000000,1,0) -> 0
H52: 43 | I52: 3.2352555e+09 | J52: =IF(I52<1700000000,1,0) -> 0
H53: 44 | I53: 3.2954715e+09 | J53: =IF(I53<1700000000,1,0) -> 0
H54: 45 | I54: 2.9860003e+09 | J54: =IF(I54<1700000000,1,0) -> 0
H55: 46 | I55: 3.2068294e+09 | J55: =IF(I55<1700000000,1,0) -> 0
... H1009: 1000 | I1009: 2.8998863e+09 | J1009: =IF(I1009<1700000000,1,0) -> 0
